{"172001":[{"address3":"Tunan","state":"Himachal Pradesh","state_code":"11","district":"Kullu","district_code":"026","address1":"Nirmand","address2":"","latitude":"31.4655","longitude":"77.6233","accuracy":"4"},{"address3":"Poshna","state":"Himachal Pradesh","state_code":"11","district":"Kullu","district_code":"026","address1":"Nirmand","address2":"","latitude":"31.4557","longitude":"77.6114","accuracy":"4"},{"address3":"Luhri","state":"Himachal Pradesh","state_code":"11","district":"Kullu","district_code":"026","address1":"Ani(S.T)","address2":"","latitude":"31.3419","longitude":"77.4301","accuracy":"4"},{"address3":"Lailon","state":"Himachal Pradesh","state_code":"11","district":"Shimla","district_code":"033","address1":"Nankhari","address2":"","latitude":"31.197","longitude":"77.6324","accuracy":"4"},{"address3":"Khaneri","state":"Himachal Pradesh","state_code":"11","district":"Shimla","district_code":"033","address1":"Rampur Bushahr","address2":"","latitude":"31.4556","longitude":"77.6623","accuracy":"4"},{"address3":"Naula","state":"Himachal Pradesh","state_code":"11","district":"Shimla","district_code":"033","address1":"Rampur(T)","address2":"","latitude":"31.3436","longitude":"77.5217","accuracy":"4"},{"address3":"Kungal Balti","state":"Himachal Pradesh","state_code":"11","district":"Shimla","district_code":"033","address1":"Rampur(T)","address2":"","latitude":"31.4903","longitude":"77.4768","accuracy":"3"},{"address3":"Shingla","state":"Himachal Pradesh","state_code":"11","district":"Shimla","district_code":"033","address1":"Rampur Bushahr","address2":"","latitude":"31.4272","longitude":"77.6326","accuracy":"4"},{"address3":"Rampur Bushahr H.O","state":"Himachal Pradesh","state_code":"11","district":"Shimla","district_code":"033","address1":"Rampur Bushahr","address2":"","latitude":"31.4903","longitude":"77.4768","accuracy":"3"},{"address3":"Surad","state":"Himachal Pradesh","state_code":"11","district":"Shimla","district_code":"033","address1":"Nankahri","address2":"","latitude":"31.326","longitude":"77.6333","accuracy":"4"},{"address3":"Padam Nagar (Shimla)","state":"Himachal Pradesh","state_code":"11","district":"Shimla","district_code":"033","address1":"Rampur(T)","address2":"","latitude":"31.4903","longitude":"77.4768","accuracy":"3"},{"address3":"Barach","state":"Himachal Pradesh","state_code":"11","district":"Shimla","district_code":"033","address1":"Nankhari","address2":"","latitude":"31.3653","longitude":"77.5618","accuracy":"4"},{"address3":"Duttnagar","state":"Himachal Pradesh","state_code":"11","district":"Shimla","district_code":"033","address1":"Rampur Bushahr","address2":"","latitude":"31.4903","longitude":"77.4768","accuracy":"3"},{"address3":"Dansa","state":"Himachal Pradesh","state_code":"11","district":"Shimla","district_code":"033","address1":"Rampur Bushahr","address2":"","latitude":"31.4185","longitude":"77.6718","accuracy":"4"},{"address3":"Nirth","state":"Himachal Pradesh","state_code":"11","district":"Shimla","district_code":"033","address1":"Rampur Bushahr","address2":"","latitude":"31.4903","longitude":"77.4768","accuracy":"3"},{"address3":"Sholi","state":"Himachal Pradesh","state_code":"11","district":"Shimla","district_code":"033","address1":"Nankhari(S.T)","address2":"","latitude":"31.315","longitude":"77.6032","accuracy":"4"},{"address3":"Thaili Chakti","state":"Himachal Pradesh","state_code":"11","district":"Shimla","district_code":"033","address1":"Rampur(T)","address2":"","latitude":"31.4903","longitude":"77.4768","accuracy":"3"},{"address3":"Khamadi","state":"Himachal Pradesh","state_code":"11","district":"Shimla","district_code":"033","address1":"Rampur(T)","address2":"","latitude":"31.3054","longitude":"77.6417","accuracy":"4"}],"172002":[{"address3":"Jaon","state":"Himachal Pradesh","state_code":"11","district":"Kullu","district_code":"026","address1":"Nermand(T)","address2":"","latitude":"31.9045","longitude":"77.4002","accuracy":"4"},{"address3":"Nishani","state":"Himachal Pradesh","state_code":"11","district":"Kullu","district_code":"026","address1":"Nirmand","address2":"","latitude":"31.5459","longitude":"77.4562","accuracy":"3"},{"address3":"Arsu","state":"Himachal Pradesh","state_code":"11","district":"Kullu","district_code":"026","address1":"Nirmand","address2":"","latitude":"31.4846","longitude":"77.5791","accuracy":"4"},{"address3":"Shamani","state":"Himachal Pradesh","state_code":"11","district":"Kullu","district_code":"026","address1":"Nermand(T)","address2":"","latitude":"31.5026","longitude":"77.5392","accuracy":"4"},{"address3":"Sarahan","state":"Himachal Pradesh","state_code":"11","district":"Kullu","district_code":"026","address1":"Nirmand","address2":"","latitude":"31.5499","longitude":"77.5378","accuracy":"4"},{"address3":"Beoni","state":"Himachal Pradesh","state_code":"11","district":"Kullu","district_code":"026","address1":"Nermand(T)","address2":"","latitude":"31.5459","longitude":"77.4562","accuracy":"3"},{"address3":"Deem","state":"Himachal Pradesh","state_code":"11","district":"Kullu","district_code":"026","address1":"Nermand(T)","address2":"","latitude":"31.5459","longitude":"77.4562","accuracy":"3"}],"172021":[{"address3":"Nankhari","state":"Himachal Pradesh","state_code":"11","district":"Shimla","district_code":"033","address1":"Nankhari","address2":"","latitude":"31.3047","longitude":"77.5838","accuracy":"4"},{"address3":"Danawali","state":"Himachal Pradesh","state_code":"11","district":"Shimla","district_code":"033","address1":"Nankhari","address2":"","latitude":"31.3047","longitude":"77.5838","accuracy":"3"}],"172022":[{"address3":"Bahli","state":"Himachal Pradesh","state_code":"11","district":"Shimla","district_code":"033","address1":"Rampur Bushahr","address2":"","latitude":"31.3251","longitude":"77.5172","accuracy":"4"},{"address3":"Taklech","state":"Himachal Pradesh","state_code":"11","district":"Shimla","district_code":"033","address1":"Rampur Bushahr","address2":"","latitude":"31.3751","longitude":"77.7315","accuracy":"4"},{"address3":"Darkali","state":"Himachal Pradesh","state_code":"11","district":"Shimla","district_code":"033","address1":"Rampur Bushahr","address2":"","latitude":"31.197","longitude":"77.6324","accuracy":"4"},{"address3":"Narain","state":"Himachal Pradesh","state_code":"11","district":"Shimla","district_code":"033","address1":"Rampur(T)","address2":"","latitude":"31.3381","longitude":"77.702","accuracy":"4"},{"address3":"Deothi","state":"Himachal Pradesh","state_code":"11","district":"Shimla","district_code":"033","address1":"Rampur Bushahr","address2":"","latitude":"31.4304","longitude":"77.7276","accuracy":"4"},{"address3":"Kashapat","state":"Himachal Pradesh","state_code":"11","district":"Shimla","district_code":"033","address1":"Rampur(T)","address2":"","latitude":"31.5135","longitude":"77.4215","accuracy":"3"},{"address3":"Nogli","state":"Himachal Pradesh","state_code":"11","district":"Shimla","district_code":"033","address1":"Rampur(T)","address2":"","latitude":"31.4014","longitude":"77.6405","accuracy":"4"},{"address3":"Kareri","state":"Himachal Pradesh","state_code":"11","district":"Shimla","district_code":"033","address1":"Rampur(T)","address2":"","latitude":"31.3737","longitude":"77.6853","accuracy":"4"},{"address3":"Bharawali","state":"Himachal Pradesh","state_code":"11","district":"Shimla","district_code":"033","address1":"Rampur(T)","address2":"","latitude":"31.5135","longitude":"77.4215","accuracy":"3"},{"address3":"Dawara","state":"Himachal Pradesh","state_code":"11","district":"Shimla","district_code":"033","address1":"Rampur Bushahr","address2":"","latitude":"31.5135","longitude":"77.4215","accuracy":"3"},{"address3":"Munish Bhali","state":"Himachal Pradesh","state_code":"11","district":"Shimla","district_code":"033","address1":"Rampur(T)","address2":"","latitude":"31.5135","longitude":"77.4215","accuracy":"3"}],"172023":[{"address3":"Jadoli","state":"Himachal Pradesh","state_code":"11","district":"Kullu","district_code":"026","address1":"Nermand(T)","address2":"","latitude":"31.4142","longitude":"77.5951","accuracy":"4"},{"address3":"Nirmand","state":"Himachal Pradesh","state_code":"11","district":"Kullu","district_code":"026","address1":"Nirmand","address2":"","latitude":"31.4314","longitude":"77.5725","accuracy":"3"},{"address3":"Ghatu","state":"Himachal Pradesh","state_code":"11","district":"Kullu","district_code":"026","address1":"Nirmand","address2":"","latitude":"31.4486","longitude":"77.5498","accuracy":"4"},{"address3":"Sharvi","state":"Himachal Pradesh","state_code":"11","district":"Kullu","district_code":"026","address1":"Nermand(T)","address2":"","latitude":"31.4314","longitude":"77.5725","accuracy":"3"},{"address3":"Koil","state":"Himachal Pradesh","state_code":"11","district":"Kullu","district_code":"026","address1":"Nermand(T)","address2":"","latitude":"31.4314","longitude":"77.5725","accuracy":"3"},{"address3":"Urtu","state":"Himachal Pradesh","state_code":"11","district":"Kullu","district_code":"026","address1":"Nermand(T)","address2":"","latitude":"31.4314","longitude":"77.5725","accuracy":"3"}],"172024":[{"address3":"Janjheli","state":"Himachal Pradesh","state_code":"11","district":"Shimla","district_code":"033","address1":"Kumarsain","address2":"","latitude":"31.3152","longitude":"77.432","accuracy":"3"},{"address3":"Kotla","state":"Himachal Pradesh","state_code":"11","district":"Shimla","district_code":"033","address1":"Kumharsain(T)","address2":"","latitude":"31.3268","longitude":"77.4162","accuracy":"4"},{"address3":"Bhareri","state":"Himachal Pradesh","state_code":"11","district":"Shimla","district_code":"033","address1":"Kumharsain(T)","address2":"","latitude":"31.3071","longitude":"77.482","accuracy":"4"},{"address3":"Chikul","state":"Himachal Pradesh","state_code":"11","district":"Shimla","district_code":"033","address1":"Kumarsain","address2":"","latitude":"31.3152","longitude":"77.432","accuracy":"3"},{"address3":"Kingal","state":"Himachal Pradesh","state_code":"11","district":"Shimla","district_code":"033","address1":"Kumarsain","address2":"","latitude":"31.3152","longitude":"77.432","accuracy":"3"},{"address3":"Galani","state":"Himachal Pradesh","state_code":"11","district":"Shimla","district_code":"033","address1":"Kumarsain","address2":"","latitude":"31.3116","longitude":"77.3979","accuracy":"4"}],"172025":[{"address3":"Dehar","state":"Himachal Pradesh","state_code":"11","district":"Kullu","district_code":"026","address1":"Ani(S.T)","address2":"","latitude":"31.9045","longitude":"77.4002","accuracy":"4"},{"address3":"Olwa","state":"Himachal Pradesh","state_code":"11","district":"Kullu","district_code":"026","address1":"Ani(S.T)","address2":"","latitude":"31.4062","longitude":"77.1252","accuracy":"3"},{"address3":"Dalash","state":"Himachal Pradesh","state_code":"11","district":"Kullu","district_code":"026","address1":"Ani(S.T)","address2":"","latitude":"31.3871","longitude":"77.4354","accuracy":"4"},{"address3":"Sush","state":"Himachal Pradesh","state_code":"11","district":"Kullu","district_code":"026","address1":"Ani(S.T)","address2":"","latitude":"31.4062","longitude":"77.1252","accuracy":"3"},{"address3":"Kandagai","state":"Himachal Pradesh","state_code":"11","district":"Kullu","district_code":"026","address1":"Ani(S.T)","address2":"","latitude":"31.4062","longitude":"77.1252","accuracy":"3"}],"172026":[{"address3":"Kothi","state":"Himachal Pradesh","state_code":"11","district":"Kullu","district_code":"026","address1":"Nermand(T)","address2":"","latitude":"31.4977","longitude":"77.3768","accuracy":"4"},{"address3":"Khanag","state":"Himachal Pradesh","state_code":"11","district":"Kullu","district_code":"026","address1":"Ani(S.T)","address2":"","latitude":"31.5184","longitude":"77.4038","accuracy":"4"},{"address3":"Kamand","state":"Himachal Pradesh","state_code":"11","district":"Kullu","district_code":"026","address1":"Ani(S.T)","address2":"","latitude":"31.4961","longitude":"77.3234","accuracy":"4"},{"address3":"Deori","state":"Himachal Pradesh","state_code":"11","district":"Kullu","district_code":"026","address1":"Ani(S.T)","address2":"","latitude":"31.9045","longitude":"77.4002","accuracy":"4"},{"address3":"Karana","state":"Himachal Pradesh","state_code":"11","district":"Kullu","district_code":"026","address1":"Anni","address2":"","latitude":"31.4551","longitude":"77.4163","accuracy":"4"},{"address3":"Anni","state":"Himachal Pradesh","state_code":"11","district":"Kullu","district_code":"026","address1":"Anni","address2":"","latitude":"31.4632","longitude":"77.4214","accuracy":"3"},{"address3":"Shawad","state":"Himachal Pradesh","state_code":"11","district":"Kullu","district_code":"026","address1":"Ani(S.T)","address2":"","latitude":"31.4406","longitude":"77.3525","accuracy":"4"},{"address3":"Nigan","state":"Himachal Pradesh","state_code":"11","district":"Kullu","district_code":"026","address1":"Ani(S.T)","address2":"","latitude":"31.4632","longitude":"77.4214","accuracy":"3"},{"address3":"Lagouti","state":"Himachal Pradesh","state_code":"11","district":"Kullu","district_code":"026","address1":"Ani(S.T)","address2":"","latitude":"31.4632","longitude":"77.4214","accuracy":"3"},{"address3":"Kandugad","state":"Himachal Pradesh","state_code":"11","district":"Kullu","district_code":"026","address1":"Ani(S.T)","address2":"","latitude":"31.4632","longitude":"77.4214","accuracy":"3"},{"address3":"Peog","state":"Himachal Pradesh","state_code":"11","district":"Kullu","district_code":"026","address1":"Ani(S.T)","address2":"","latitude":"31.4632","longitude":"77.4214","accuracy":"3"},{"address3":"Duhad","state":"Himachal Pradesh","state_code":"11","district":"Kullu","district_code":"026","address1":"Anni","address2":"","latitude":"31.4632","longitude":"77.4214","accuracy":"3"},{"address3":"Khunn","state":"Himachal Pradesh","state_code":"11","district":"Kullu","district_code":"026","address1":"Ani(S.T)","address2":"","latitude":"31.4632","longitude":"77.4214","accuracy":"3"},{"address3":"Digerh","state":"Himachal Pradesh","state_code":"11","district":"Kullu","district_code":"026","address1":"Ani(S.T)","address2":"","latitude":"31.4632","longitude":"77.4214","accuracy":"3"}],"172027":[{"address3":"Teshan","state":"Himachal Pradesh","state_code":"11","district":"Shimla","district_code":"033","address1":"Kumharsain(T)","address2":"","latitude":"31.3546","longitude":"77.3988","accuracy":"4"},{"address3":"Shiwan","state":"Himachal Pradesh","state_code":"11","district":"Shimla","district_code":"033","address1":"Kumharsain(T)","address2":"","latitude":"31.3489","longitude":"77.3862","accuracy":"3"},{"address3":"Baragaon (Shimla)","state":"Himachal Pradesh","state_code":"11","district":"Shimla","district_code":"033","address1":"Kumarsain","address2":"","latitude":"31.3433","longitude":"77.3736","accuracy":"4"}],"172028":[{"address3":"Delath","state":"Himachal Pradesh","state_code":"11","district":"Shimla","district_code":"033","address1":"Nankhari(S.T)","address2":"","latitude":"31.3401","longitude":"77.5429","accuracy":"4"}],"172029":[{"address3":"Pharal","state":"Himachal Pradesh","state_code":"11","district":"Shimla","district_code":"033","address1":"Kumharsain(T)","address2":"","latitude":"31.2984","longitude":"77.4277","accuracy":"4"},{"address3":"Kumarsain","state":"Himachal Pradesh","state_code":"11","district":"Shimla","district_code":"033","address1":"Kumarsain","address2":"","latitude":"31.3059","longitude":"77.4293","accuracy":"3"},{"address3":"Jar","state":"Himachal Pradesh","state_code":"11","district":"Shimla","district_code":"033","address1":"Kumharsain(T)","address2":"","latitude":"31.3133","longitude":"77.431","accuracy":"4"},{"address3":"Sharambal Camp","state":"Himachal Pradesh","state_code":"11","district":"Shimla","district_code":"033","address1":"Kumarsain","address2":"","latitude":"31.3059","longitude":"77.4293","accuracy":"3"}],"172030":[{"address3":"Thanedhar","state":"Himachal Pradesh","state_code":"11","district":"Shimla","district_code":"033","address1":"Kumharsain(T)","address2":"","latitude":"31.197","longitude":"77.6324","accuracy":"4"},{"address3":"Bhutti","state":"Himachal Pradesh","state_code":"11","district":"Shimla","district_code":"033","address1":"Kumarsain","address2":"","latitude":"31.3318","longitude":"77.5279","accuracy":"4"},{"address3":"Kirti","state":"Himachal Pradesh","state_code":"11","district":"Shimla","district_code":"033","address1":"Kumarsain","address2":"","latitude":"31.3307","longitude":"77.4614","accuracy":"4"},{"address3":"Shamathla","state":"Himachal Pradesh","state_code":"11","district":"Shimla","district_code":"033","address1":"Kumharsain(T)","address2":"","latitude":"31.3357","longitude":"77.5023","accuracy":"4"},{"address3":"Virgarh","state":"Himachal Pradesh","state_code":"11","district":"Kinnaur","district_code":"034","address1":"Nichar(T)","address2":"","latitude":"31.3461","longitude":"77.4899","accuracy":"3"}],"172031":[{"address3":"Batari","state":"Himachal Pradesh","state_code":"11","district":"Shimla","district_code":"033","address1":"Kumharsain(T)","address2":"","latitude":"31.2893","longitude":"77.4852","accuracy":"4"},{"address3":"Kotgarh","state":"Himachal Pradesh","state_code":"11","district":"Shimla","district_code":"033","address1":"Kumharsain(T)","address2":"","latitude":"31.3125","longitude":"77.4797","accuracy":"4"},{"address3":"Jarol","state":"Himachal Pradesh","state_code":"11","district":"Shimla","district_code":"033","address1":"Kumharsain(T)","address2":"","latitude":"31.2909","longitude":"77.4976","accuracy":"4"}],"172032":[{"address3":"Jaon","state":"Himachal Pradesh","state_code":"11","district":"Kullu","district_code":"026","address1":"Nermand(T)","address2":"","latitude":"31.9045","longitude":"77.4002","accuracy":"4"},{"address3":"Gad","state":"Himachal Pradesh","state_code":"11","district":"Kullu","district_code":"026","address1":"Anni","address2":"","latitude":"31.4283","longitude":"77.4713","accuracy":"4"},{"address3":"Chowai","state":"Himachal Pradesh","state_code":"11","district":"Kullu","district_code":"026","address1":"Ani(S.T)","address2":"","latitude":"31.5373","longitude":"77.3201","accuracy":"3"}],"172033":[{"address3":"Tandi","state":"Himachal Pradesh","state_code":"11","district":"Kullu","district_code":"026","address1":"Nermand(T)","address2":"","latitude":"31.384","longitude":"77.4902","accuracy":"4"},{"address3":"Durah","state":"Himachal Pradesh","state_code":"11","district":"Kullu","district_code":"026","address1":"Nermand(T)","address2":"","latitude":"31.384","longitude":"77.4902","accuracy":"3"},{"address3":"Nither","state":"Himachal Pradesh","state_code":"11","district":"Kullu","district_code":"026","address1":"Nirmand","address2":"","latitude":"31.384","longitude":"77.4902","accuracy":"3"}],"172034":[{"address3":"Bonda","state":"Himachal Pradesh","state_code":"11","district":"Shimla","district_code":"033","address1":"Rampur(T)","address2":"","latitude":"31.3736","longitude":"77.4552","accuracy":"1"}],"172101":[{"address3":"Rupi","state":"Himachal Pradesh","state_code":"11","district":"Shimla","district_code":"033","address1":"Rampur(T)","address2":"","latitude":"31.197","longitude":"77.6324","accuracy":"4"},{"address3":"Ganvi","state":"Himachal Pradesh","state_code":"11","district":"Shimla","district_code":"033","address1":"Rampur Bushahr","address2":"","latitude":"31.5062","longitude":"77.3347","accuracy":"3"},{"address3":"Koot","state":"Himachal Pradesh","state_code":"11","district":"Shimla","district_code":"033","address1":"Rampur(T)","address2":"","latitude":"31.5062","longitude":"77.3347","accuracy":"3"},{"address3":"Labana","state":"Himachal Pradesh","state_code":"11","district":"Shimla","district_code":"033","address1":"Rampur Bushahr","address2":"","latitude":"31.197","longitude":"77.6324","accuracy":"4"},{"address3":"Jaghori","state":"Himachal Pradesh","state_code":"11","district":"Shimla","district_code":"033","address1":"Rampur(T)","address2":"","latitude":"31.5062","longitude":"77.3347","accuracy":"3"},{"address3":"Phancha","state":"Himachal Pradesh","state_code":"11","district":"Shimla","district_code":"033","address1":"Rampur Bushahr","address2":"","latitude":"31.5971","longitude":"77.7336","accuracy":"4"},{"address3":"Kayab","state":"Himachal Pradesh","state_code":"11","district":"Shimla","district_code":"033","address1":"Rampur(T)","address2":"","latitude":"31.5062","longitude":"77.3347","accuracy":"3"},{"address3":"Jeori","state":"Himachal Pradesh","state_code":"11","district":"Shimla","district_code":"033","address1":"Rampur(T)","address2":"","latitude":"31.197","longitude":"77.6324","accuracy":"4"},{"address3":"Chaura","state":"Himachal Pradesh","state_code":"11","district":"Kinnaur","district_code":"034","address1":"Nichar(T)","address2":"","latitude":"31.5968","longitude":"78.4126","accuracy":"4"},{"address3":"Taranda","state":"Himachal Pradesh","state_code":"11","district":"Kinnaur","district_code":"034","address1":"Nichar(T)","address2":"","latitude":"31.5062","longitude":"77.3347","accuracy":"3"},{"address3":"Nigulsari","state":"Himachal Pradesh","state_code":"11","district":"Kinnaur","district_code":"034","address1":"Nichar(T)","address2":"","latitude":"31.5062","longitude":"77.3347","accuracy":"3"},{"address3":"Chota Khamba","state":"Himachal Pradesh","state_code":"11","district":"Kinnaur","district_code":"034","address1":"Nichar(T)","address2":"","latitude":"31.5062","longitude":"77.3347","accuracy":"3"}],"172102":[{"address3":"Sarahan BSR","state":"Himachal Pradesh","state_code":"11","district":"Shimla","district_code":"033","address1":"Rampur Bushahr","address2":"","latitude":"31.5276","longitude":"78.0946","accuracy":"1"},{"address3":"Mashnoo","state":"Himachal Pradesh","state_code":"11","district":"Shimla","district_code":"033","address1":"Rampur(T)","address2":"","latitude":"31.5276","longitude":"78.0946","accuracy":"1"},{"address3":"Dofda","state":"Himachal Pradesh","state_code":"11","district":"Shimla","district_code":"033","address1":"Rampur(T)","address2":"","latitude":"31.5276","longitude":"78.0946","accuracy":"1"},{"address3":"Shahdhar","state":"Himachal Pradesh","state_code":"11","district":"Shimla","district_code":"033","address1":"Rampur Bushahr","address2":"","latitude":"31.5276","longitude":"78.0946","accuracy":"1"},{"address3":"Majauli","state":"Himachal Pradesh","state_code":"11","district":"Shimla","district_code":"033","address1":"Rampur Bushahr","address2":"","latitude":"31.5276","longitude":"78.0946","accuracy":"1"},{"address3":"Kinnu","state":"Himachal Pradesh","state_code":"11","district":"Shimla","district_code":"033","address1":"Rampur Bushahr","address2":"","latitude":"31.5276","longitude":"78.0946","accuracy":"1"}],"172103":[{"address3":"Nichar","state":"Himachal Pradesh","state_code":"11","district":"Kinnaur","district_code":"034","address1":"Nichar(T)","address2":"","latitude":"31.5276","longitude":"78.0946","accuracy":"1"}],"172104":[{"address3":"Chagaon","state":"Himachal Pradesh","state_code":"11","district":"Kinnaur","district_code":"034","address1":"Nichar(T)","address2":"","latitude":"31.5299","longitude":"78.0895","accuracy":"4"},{"address3":"Mirro","state":"Himachal Pradesh","state_code":"11","district":"Kinnaur","district_code":"034","address1":"Nichar(T)","address2":"","latitude":"31.5225","longitude":"78.0935","accuracy":"3"},{"address3":"Urni","state":"Himachal Pradesh","state_code":"11","district":"Kinnaur","district_code":"034","address1":"Nichar(T)","address2":"","latitude":"31.5312","longitude":"78.1247","accuracy":"4"},{"address3":"Panvi","state":"Himachal Pradesh","state_code":"11","district":"Kinnaur","district_code":"034","address1":"Nichar(T)","address2":"","latitude":"31.5225","longitude":"78.0935","accuracy":"3"},{"address3":"Wangtoo","state":"Himachal Pradesh","state_code":"11","district":"Kinnaur","district_code":"034","address1":"Nichar(T)","address2":"","latitude":"31.5225","longitude":"78.0935","accuracy":"3"},{"address3":"Tapri","state":"Himachal Pradesh","state_code":"11","district":"Kinnaur","district_code":"034","address1":"Nichar(T)","address2":"","latitude":"31.5191","longitude":"78.1014","accuracy":"4"},{"address3":"Yulla","state":"Himachal Pradesh","state_code":"11","district":"Kinnaur","district_code":"034","address1":"Nichar(T)","address2":"","latitude":"31.5225","longitude":"78.0935","accuracy":"3"},{"address3":"Ramni","state":"Himachal Pradesh","state_code":"11","district":"Kinnaur","district_code":"034","address1":"Nichar","address2":"","latitude":"31.5097","longitude":"78.0583","accuracy":"4"}],"172105":[{"address3":"Brua","state":"Himachal Pradesh","state_code":"11","district":"Kinnaur","district_code":"034","address1":"Sangla(T)","address2":"","latitude":"31.5005","longitude":"78.1631","accuracy":"3"},{"address3":"Shong","state":"Himachal Pradesh","state_code":"11","district":"Kinnaur","district_code":"034","address1":"Sangla(T)","address2":"","latitude":"31.5005","longitude":"78.1631","accuracy":"3"},{"address3":"Sapni","state":"Himachal Pradesh","state_code":"11","district":"Kinnaur","district_code":"034","address1":"Sangla(T)","address2":"","latitude":"31.4864","longitude":"78.1684","accuracy":"4"},{"address3":"Kilba","state":"Himachal Pradesh","state_code":"11","district":"Kinnaur","district_code":"034","address1":"Nichar(T)","address2":"","latitude":"31.5142","longitude":"78.1454","accuracy":"4"},{"address3":"Karcham","state":"Himachal Pradesh","state_code":"11","district":"Kinnaur","district_code":"034","address1":"Sangla(T)","address2":"","latitude":"31.5009","longitude":"78.1756","accuracy":"4"}],"172106":[{"address3":"Rakchham","state":"Himachal Pradesh","state_code":"11","district":"Kinnaur","district_code":"034","address1":"Sangla(T)","address2":"","latitude":"31.3913","longitude":"78.3506","accuracy":"3"},{"address3":"Chansu","state":"Himachal Pradesh","state_code":"11","district":"Kinnaur","district_code":"034","address1":"Sangla(T)","address2":"","latitude":"31.3913","longitude":"78.3506","accuracy":"3"},{"address3":"Kamroo","state":"Himachal Pradesh","state_code":"11","district":"Kinnaur","district_code":"034","address1":"Sangla","address2":"","latitude":"31.3913","longitude":"78.3506","accuracy":"3"},{"address3":"Chitkul","state":"Himachal Pradesh","state_code":"11","district":"Kinnaur","district_code":"034","address1":"Sangla(T)","address2":"","latitude":"31.3531","longitude":"78.4355","accuracy":"4"},{"address3":"Batseri","state":"Himachal Pradesh","state_code":"11","district":"Kinnaur","district_code":"034","address1":"Sangla(T)","address2":"","latitude":"31.3913","longitude":"78.3506","accuracy":"3"},{"address3":"Sangla","state":"Himachal Pradesh","state_code":"11","district":"Kinnaur","district_code":"034","address1":"Sangla(T)","address2":"","latitude":"31.4295","longitude":"78.2657","accuracy":"4"}],"172107":[{"address3":"Reckong Peo H.O","state":"Himachal Pradesh","state_code":"11","district":"Kinnaur","district_code":"034","address1":"Kalpa(T)","address2":"","latitude":"31.5586","longitude":"78.2755","accuracy":"3"},{"address3":"Barang","state":"Himachal Pradesh","state_code":"11","district":"Kinnaur","district_code":"034","address1":"Kalpa(T)","address2":"","latitude":"31.5108","longitude":"78.2654","accuracy":"4"},{"address3":"Powari","state":"Himachal Pradesh","state_code":"11","district":"Kinnaur","district_code":"034","address1":"Kalpa(T)","address2":"","latitude":"31.5586","longitude":"78.2755","accuracy":"3"},{"address3":"Khawangi","state":"Himachal Pradesh","state_code":"11","district":"Kinnaur","district_code":"034","address1":"Kalpa(T)","address2":"","latitude":"31.5474","longitude":"78.2711","accuracy":"4"},{"address3":"Meber","state":"Himachal Pradesh","state_code":"11","district":"Kinnaur","district_code":"034","address1":"Kalpa(T)","address2":"","latitude":"31.5586","longitude":"78.2755","accuracy":"3"},{"address3":"Kothi","state":"Himachal Pradesh","state_code":"11","district":"Kinnaur","district_code":"034","address1":"Kalpa(T)","address2":"","latitude":"31.5512","longitude":"78.2665","accuracy":"4"},{"address3":"Purbani","state":"Himachal Pradesh","state_code":"11","district":"Kinnaur","district_code":"034","address1":"Kalpa(T)","address2":"","latitude":"31.5913","longitude":"78.2987","accuracy":"4"},{"address3":"Pangi","state":"Himachal Pradesh","state_code":"11","district":"Kinnaur","district_code":"034","address1":"Kalpa(T)","address2":"","latitude":"31.5922","longitude":"78.2761","accuracy":"4"}],"172108":[{"address3":"Duni","state":"Himachal Pradesh","state_code":"11","district":"Kinnaur","district_code":"034","address1":"Kalpa(T)","address2":"","latitude":"31.5551","longitude":"78.2602","accuracy":"4"},{"address3":"Roghi","state":"Himachal Pradesh","state_code":"11","district":"Kinnaur","district_code":"034","address1":"Kalpa(T)","address2":"","latitude":"31.5088","longitude":"78.2222","accuracy":"4"},{"address3":"Kalpa","state":"Himachal Pradesh","state_code":"11","district":"Kinnaur","district_code":"034","address1":"Kalpa(T)","address2":"","latitude":"31.5331","longitude":"78.2688","accuracy":"4"}],"172109":[{"address3":"Kunnu","state":"Himachal Pradesh","state_code":"11","district":"Kinnaur","district_code":"034","address1":"Morang(T)","address2":"","latitude":"31.5901","longitude":"78.4372","accuracy":"3"},{"address3":"Charang","state":"Himachal Pradesh","state_code":"11","district":"Kinnaur","district_code":"034","address1":"Morang(T)","address2":"","latitude":"31.4513","longitude":"78.5684","accuracy":"4"},{"address3":"Moorang","state":"Himachal Pradesh","state_code":"11","district":"Kinnaur","district_code":"034","address1":"Morang(T)","address2":"","latitude":"31.5901","longitude":"78.4372","accuracy":"3"},{"address3":"Thangi","state":"Himachal Pradesh","state_code":"11","district":"Kinnaur","district_code":"034","address1":"Morang(T)","address2":"","latitude":"31.5552","longitude":"78.4832","accuracy":"4"},{"address3":"Lippa","state":"Himachal Pradesh","state_code":"11","district":"Kinnaur","district_code":"034","address1":"Morang(T)","address2":"","latitude":"31.6657","longitude":"78.3842","accuracy":"4"},{"address3":"Asrang","state":"Himachal Pradesh","state_code":"11","district":"Kinnaur","district_code":"034","address1":"Moorang","address2":"","latitude":"31.6665","longitude":"78.3199","accuracy":"4"},{"address3":"Jangi","state":"Himachal Pradesh","state_code":"11","district":"Kinnaur","district_code":"034","address1":"Morang(T)","address2":"","latitude":"31.6118","longitude":"78.4305","accuracy":"4"}],"172110":[{"address3":"Ropa","state":"Himachal Pradesh","state_code":"11","district":"Kinnaur","district_code":"034","address1":"Poo(T)","address2":"","latitude":"31.5968","longitude":"78.4126","accuracy":"4"},{"address3":"Speelo","state":"Himachal Pradesh","state_code":"11","district":"Kinnaur","district_code":"034","address1":"Poo(T)","address2":"","latitude":"31.6421","longitude":"78.1822","accuracy":"3"},{"address3":"Giabong","state":"Himachal Pradesh","state_code":"11","district":"Kinnaur","district_code":"034","address1":"Morang(T)","address2":"","latitude":"31.7576","longitude":"78.4683","accuracy":"4"},{"address3":"Sunnam","state":"Himachal Pradesh","state_code":"11","district":"Kinnaur","district_code":"034","address1":"Poo(T)","address2":"","latitude":"31.6421","longitude":"78.1822","accuracy":"3"},{"address3":"Kanam","state":"Himachal Pradesh","state_code":"11","district":"Kinnaur","district_code":"034","address1":"Poo(T)","address2":"","latitude":"31.6757","longitude":"78.4552","accuracy":"4"},{"address3":"Shiaso","state":"Himachal Pradesh","state_code":"11","district":"Kinnaur","district_code":"034","address1":"Poo(T)","address2":"","latitude":"31.6421","longitude":"78.1822","accuracy":"3"},{"address3":"Labrang","state":"Himachal Pradesh","state_code":"11","district":"Kinnaur","district_code":"034","address1":"Poo(T)","address2":"","latitude":"31.6794","longitude":"78.4437","accuracy":"4"},{"address3":"Nesang","state":"Himachal Pradesh","state_code":"11","district":"Kinnaur","district_code":"034","address1":"Poo(T)","address2":"","latitude":"31.6421","longitude":"78.1822","accuracy":"3"}],"172111":[{"address3":"Nako","state":"Himachal Pradesh","state_code":"11","district":"Kinnaur","district_code":"034","address1":"Hangrang","address2":"","latitude":"31.8888","longitude":"78.6183","accuracy":"4"},{"address3":"Chango","state":"Himachal Pradesh","state_code":"11","district":"Kinnaur","district_code":"034","address1":"Poo(T)","address2":"","latitude":"31.9148","longitude":"78.5854","accuracy":"3"},{"address3":"Namgia","state":"Himachal Pradesh","state_code":"11","district":"Kinnaur","district_code":"034","address1":"Poo(T)","address2":"","latitude":"31.8045","longitude":"78.6467","accuracy":"4"},{"address3":"Pooh","state":"Himachal Pradesh","state_code":"11","district":"Kinnaur","district_code":"034","address1":"Pooh","address2":"","latitude":"31.9148","longitude":"78.5854","accuracy":"3"},{"address3":"Sumra","state":"Himachal Pradesh","state_code":"11","district":"Kinnaur","district_code":"034","address1":"Pooh","address2":"","latitude":"31.5968","longitude":"78.4126","accuracy":"4"},{"address3":"Pooh Gaon","state":"Himachal Pradesh","state_code":"11","district":"Kinnaur","district_code":"034","address1":"Poo(T)","address2":"","latitude":"31.9148","longitude":"78.5854","accuracy":"3"},{"address3":"Shalkhar","state":"Himachal Pradesh","state_code":"11","district":"Kinnaur","district_code":"034","address1":"Poo(T)","address2":"","latitude":"31.9148","longitude":"78.5854","accuracy":"3"},{"address3":"Samdoo","state":"Himachal Pradesh","state_code":"11","district":"Kinnaur","district_code":"034","address1":"Poo(T)","address2":"","latitude":"31.9148","longitude":"78.5854","accuracy":"3"},{"address3":"Gue","state":"Himachal Pradesh","state_code":"11","district":"Kinnaur","district_code":"034","address1":"Poo(T)","address2":"","latitude":"31.9148","longitude":"78.5854","accuracy":"3"},{"address3":"Dubling","state":"Himachal Pradesh","state_code":"11","district":"Kinnaur","district_code":"034","address1":"Poo(T)","address2":"","latitude":"31.9148","longitude":"78.5854","accuracy":"3"}],"172112":[{"address3":"Hango","state":"Himachal Pradesh","state_code":"11","district":"Kinnaur","district_code":"034","address1":"Hangrang","address2":"","latitude":"31.826","longitude":"78.0869","accuracy":"1"},{"address3":"Liyo","state":"Himachal Pradesh","state_code":"11","district":"Kinnaur","district_code":"034","address1":"Hangrang","address2":"","latitude":"31.826","longitude":"78.0869","accuracy":"1"}],"172113":[{"address3":"Mane","state":"Himachal Pradesh","state_code":"11","district":"Lahul & Spiti","district_code":"025","address1":"Spiti       (T)","address2":"","latitude":"32.4805","longitude":"77.6161","accuracy":"4"},{"address3":"Dhanker","state":"Himachal Pradesh","state_code":"11","district":"Lahul & Spiti","district_code":"025","address1":"Spiti","address2":"","latitude":"32.3735","longitude":"77.2418","accuracy":"3"},{"address3":"Tabo","state":"Himachal Pradesh","state_code":"11","district":"Lahul & Spiti","district_code":"025","address1":"Spiti","address2":"","latitude":"32.0899","longitude":"78.3721","accuracy":"4"},{"address3":"Lalung","state":"Himachal Pradesh","state_code":"11","district":"Lahul & Spiti","district_code":"025","address1":"Spiti       (T)","address2":"","latitude":"32.3735","longitude":"77.2418","accuracy":"3"}],"172114":[{"address3":"Hansa","state":"Himachal Pradesh","state_code":"11","district":"Lahul & Spiti","district_code":"025","address1":"Spiti","address2":"","latitude":"32.1586","longitude":"78.1313","accuracy":"3"},{"address3":"Lara","state":"Himachal Pradesh","state_code":"11","district":"Lahul & Spiti","district_code":"025","address1":"Spiti       (T)","address2":"","latitude":"32.1586","longitude":"78.1313","accuracy":"4"},{"address3":"Kaza","state":"Himachal Pradesh","state_code":"11","district":"Lahul & Spiti","district_code":"025","address1":"Spiti       (T)","address2":"","latitude":"32.1586","longitude":"78.1313","accuracy":"3"},{"address3":"Kee Gompa","state":"Himachal Pradesh","state_code":"11","district":"Lahul & Spiti","district_code":"025","address1":"Spiti       (T)","address2":"","latitude":"32.1586","longitude":"78.1313","accuracy":"3"},{"address3":"Demul","state":"Himachal Pradesh","state_code":"11","district":"Lahul & Spiti","district_code":"025","address1":"Spiti","address2":"","latitude":"32.1586","longitude":"78.1313","accuracy":"3"},{"address3":"Hikkam","state":"Himachal Pradesh","state_code":"11","district":"Lahul & Spiti","district_code":"025","address1":"Spiti","address2":"","latitude":"32.1586","longitude":"78.1313","accuracy":"3"},{"address3":"Rangrik","state":"Himachal Pradesh","state_code":"11","district":"Lahul & Spiti","district_code":"025","address1":"Spiti       (T)","address2":"","latitude":"32.1586","longitude":"78.1313","accuracy":"3"},{"address3":"Hull","state":"Himachal Pradesh","state_code":"11","district":"Lahul & Spiti","district_code":"025","address1":"Spiti       (T)","address2":"","latitude":"32.1586","longitude":"78.1313","accuracy":"3"},{"address3":"Losser","state":"Himachal Pradesh","state_code":"11","district":"Lahul & Spiti","district_code":"025","address1":"Spiti       (T)","address2":"","latitude":"32.1586","longitude":"78.1313","accuracy":"3"},{"address3":"Kibber","state":"Himachal Pradesh","state_code":"11","district":"Lahul & Spiti","district_code":"025","address1":"Spiti       (T)","address2":"","latitude":"32.1586","longitude":"78.1313","accuracy":"3"}],"172115":[{"address3":"Bhaba Nagar","state":"Himachal Pradesh","state_code":"11","district":"Kinnaur","district_code":"034","address1":"Nichar(T)","address2":"","latitude":"32.0518","longitude":"76.7184","accuracy":"3"},{"address3":"Bari","state":"Himachal Pradesh","state_code":"11","district":"Kinnaur","district_code":"034","address1":"Nichar(T)","address2":"","latitude":"31.5968","longitude":"78.4126","accuracy":"4"},{"address3":"Sungra","state":"Himachal Pradesh","state_code":"11","district":"Kinnaur","district_code":"034","address1":"Nichar(T)","address2":"","latitude":"32.0518","longitude":"76.7184","accuracy":"3"},{"address3":"Ponda Solding","state":"Himachal Pradesh","state_code":"11","district":"Kinnaur","district_code":"034","address1":"Nichar(T)","address2":"","latitude":"32.0518","longitude":"76.7184","accuracy":"3"},{"address3":"Nathpa","state":"Himachal Pradesh","state_code":"11","district":"Kinnaur","district_code":"034","address1":"Nichar","address2":"","latitude":"32.0518","longitude":"76.7184","accuracy":"3"}],"172116":[{"address3":"Ribba","state":"Himachal Pradesh","state_code":"11","district":"Kinnaur","district_code":"034","address1":"Morang(T)","address2":"","latitude":"31.5881","longitude":"78.3639","accuracy":"4"},{"address3":"Akpa","state":"Himachal Pradesh","state_code":"11","district":"Kinnaur","district_code":"034","address1":"Poo(T)","address2":"","latitude":"31.5856","longitude":"78.391","accuracy":"4"},{"address3":"Rarang","state":"Himachal Pradesh","state_code":"11","district":"Kinnaur","district_code":"034","address1":"Pooh","address2":"","latitude":"31.602","longitude":"78.3541","accuracy":"4"},{"address3":"Rispa","state":"Himachal Pradesh","state_code":"11","district":"Kinnaur","district_code":"034","address1":"Morang(T)","address2":"","latitude":"31.5762","longitude":"78.4268","accuracy":"4"}],"172117":[{"address3":"Mud","state":"Himachal Pradesh","state_code":"11","district":"Lahul & Spiti","district_code":"025","address1":"Spiti       (T)","address2":"","latitude":"31.826","longitude":"78.0869","accuracy":"1"},{"address3":"Sagnam","state":"Himachal Pradesh","state_code":"11","district":"Lahul & Spiti","district_code":"025","address1":"Spiti       (T)","address2":"","latitude":"31.826","longitude":"78.0869","accuracy":"1"},{"address3":"Gulling","state":"Himachal Pradesh","state_code":"11","district":"Lahul & Spiti","district_code":"025","address1":"Spiti","address2":"","latitude":"31.826","longitude":"78.0869","accuracy":"1"}],"172118":[{"address3":"Bhaba","state":"Himachal Pradesh","state_code":"11","district":"Kinnaur","district_code":"034","address1":"Nichar(T)","address2":"","latitude":"31.5932","longitude":"78.0371","accuracy":"3"},{"address3":"Katgaon","state":"Himachal Pradesh","state_code":"11","district":"Kinnaur","district_code":"034","address1":"Nichar(T)","address2":"","latitude":"31.5932","longitude":"78.0371","accuracy":"4"}],"172201":[{"address3":"Kushwa","state":"Himachal Pradesh","state_code":"11","district":"Kullu","district_code":"026","address1":"Nirmand","address2":"","latitude":"31.5181","longitude":"77.688","accuracy":"4"},{"address3":"Sargha","state":"Himachal Pradesh","state_code":"11","district":"Kullu","district_code":"026","address1":"Nirmand","address2":"","latitude":"31.5325","longitude":"77.6833","accuracy":"4"},{"address3":"Sugha","state":"Himachal Pradesh","state_code":"11","district":"Shimla","district_code":"033","address1":"Rampur(T)","address2":"","latitude":"31.6716","longitude":"77.4231","accuracy":"3"},{"address3":"Sarpara","state":"Himachal Pradesh","state_code":"11","district":"Shimla","district_code":"033","address1":"Rampur(T)","address2":"","latitude":"31.5501","longitude":"77.7153","accuracy":"4"},{"address3":"Gaura","state":"Himachal Pradesh","state_code":"11","district":"Shimla","district_code":"033","address1":"Rampur Bushahr","address2":"","latitude":"31.4809","longitude":"77.7175","accuracy":"4"},{"address3":"Kharga","state":"Himachal Pradesh","state_code":"11","district":"Shimla","district_code":"033","address1":"Rampur(T)","address2":"","latitude":"31.197","longitude":"77.6324","accuracy":"4"},{"address3":"Jhakri","state":"Himachal Pradesh","state_code":"11","district":"Shimla","district_code":"033","address1":"Rampur(T)","address2":"","latitude":"31.197","longitude":"77.6324","accuracy":"4"},{"address3":"Kartot","state":"Himachal Pradesh","state_code":"11","district":"Shimla","district_code":"033","address1":"Rampur Bushahr","address2":"","latitude":"31.4921","longitude":"77.7412","accuracy":"4"}],"credits":[{"name":"geonames","url":"https://www.geonames.org"}],"last_update":"2019-03-01T09:01:30.547Z"}