{"327001":[{"address3":"Thikariya","state":"Rajasthan","state_code":"24","district":"Banswara","district_code":"125","address1":"Banswara","address2":"","latitude":"24.1534","longitude":"74.3421","accuracy":"3"},{"address3":"Rohida","state":"Rajasthan","state_code":"24","district":"Banswara","district_code":"125","address1":"Banswara","address2":"","latitude":"23.4752","longitude":"74.3639","accuracy":"4"},{"address3":"Panchalwasa","state":"Rajasthan","state_code":"24","district":"Banswara","district_code":"125","address1":"Banswara","address2":"","latitude":"24.1534","longitude":"74.3421","accuracy":"3"},{"address3":"Sundni","state":"Rajasthan","state_code":"24","district":"Banswara","district_code":"125","address1":"Banswara","address2":"","latitude":"23.6873","longitude":"74.3075","accuracy":"4"},{"address3":"Kundal","state":"Rajasthan","state_code":"24","district":"Banswara","district_code":"125","address1":"Banswara","address2":"","latitude":"23.4752","longitude":"74.3639","accuracy":"4"},{"address3":"Singhpura","state":"Rajasthan","state_code":"24","district":"Banswara","district_code":"125","address1":"Banswara","address2":"","latitude":"23.4752","longitude":"74.3639","accuracy":"3"},{"address3":"Fefar","state":"Rajasthan","state_code":"24","district":"Banswara","district_code":"125","address1":"Banswara","address2":"","latitude":"24.1534","longitude":"74.3421","accuracy":"3"},{"address3":"Khandu","state":"Rajasthan","state_code":"24","district":"Banswara","district_code":"125","address1":"Banswara","address2":"","latitude":"23.4591","longitude":"74.5413","accuracy":"4"},{"address3":"Tamtiya","state":"Rajasthan","state_code":"24","district":"Banswara","district_code":"125","address1":"Banswara","address2":"","latitude":"24.1534","longitude":"74.3421","accuracy":"3"},{"address3":"Surpur","state":"Rajasthan","state_code":"24","district":"Banswara","district_code":"125","address1":"Banswara","address2":"","latitude":"23.4752","longitude":"74.3639","accuracy":"4"},{"address3":"Godi Tajpur","state":"Rajasthan","state_code":"24","district":"Banswara","district_code":"125","address1":"Banswara","address2":"","latitude":"24.1534","longitude":"74.3421","accuracy":"3"},{"address3":"Jhupel","state":"Rajasthan","state_code":"24","district":"Banswara","district_code":"125","address1":"Banswara","address2":"","latitude":"23.4526","longitude":"74.4383","accuracy":"4"},{"address3":"Lodha","state":"Rajasthan","state_code":"24","district":"Banswara","district_code":"125","address1":"Banswara","address2":"","latitude":"23.4752","longitude":"74.3639","accuracy":"4"},{"address3":"Tajpur","state":"Rajasthan","state_code":"24","district":"Banswara","district_code":"125","address1":"Banswara","address2":"","latitude":"23.4752","longitude":"74.3639","accuracy":"3"},{"address3":"Chacha Kota","state":"Rajasthan","state_code":"24","district":"Banswara","district_code":"125","address1":"Banswara","address2":"","latitude":"24.1534","longitude":"74.3421","accuracy":"3"},{"address3":"Banswara Ind. Area","state":"Rajasthan","state_code":"24","district":"Banswara","district_code":"125","address1":"Banswara","address2":"","latitude":"24.1534","longitude":"74.3421","accuracy":"3"},{"address3":"Napla","state":"Rajasthan","state_code":"24","district":"Banswara","district_code":"125","address1":"Banswara","address2":"","latitude":"24.1534","longitude":"74.3421","accuracy":"3"},{"address3":"Harnathpura","state":"Rajasthan","state_code":"24","district":"Banswara","district_code":"125","address1":"Banswara","address2":"","latitude":"23.4752","longitude":"74.3639","accuracy":"4"},{"address3":"Jahapura","state":"Rajasthan","state_code":"24","district":"Banswara","district_code":"125","address1":"Banswara","address2":"","latitude":"24.1534","longitude":"74.3421","accuracy":"3"},{"address3":"Badgoan","state":"Rajasthan","state_code":"24","district":"Banswara","district_code":"125","address1":"Banswara","address2":"","latitude":"24.1534","longitude":"74.3421","accuracy":"3"},{"address3":"Kaserpura","state":"Rajasthan","state_code":"24","district":"Banswara","district_code":"125","address1":"Banswara","address2":"","latitude":"24.1534","longitude":"74.3421","accuracy":"3"},{"address3":"Maheshpura","state":"Rajasthan","state_code":"24","district":"Banswara","district_code":"125","address1":"Banswara","address2":"","latitude":"23.4752","longitude":"74.3639","accuracy":"4"},{"address3":"Kundla Kalan","state":"Rajasthan","state_code":"24","district":"Banswara","district_code":"125","address1":"Banswara","address2":"","latitude":"24.1534","longitude":"74.3421","accuracy":"3"},{"address3":"Upla Ghantala","state":"Rajasthan","state_code":"24","district":"Banswara","district_code":"125","address1":"Banswara","address2":"","latitude":"24.1534","longitude":"74.3421","accuracy":"3"},{"address3":"Kheda Khas","state":"Rajasthan","state_code":"24","district":"Banswara","district_code":"125","address1":"Banswara","address2":"","latitude":"24.1534","longitude":"74.3421","accuracy":"3"},{"address3":"Khajuri","state":"Rajasthan","state_code":"24","district":"Banswara","district_code":"125","address1":"Banswara","address2":"","latitude":"23.6021","longitude":"74.6269","accuracy":"4"},{"address3":"Nichala Ghantala","state":"Rajasthan","state_code":"24","district":"Banswara","district_code":"125","address1":"Banswara","address2":"","latitude":"24.1534","longitude":"74.3421","accuracy":"3"},{"address3":"Banswara City","state":"Rajasthan","state_code":"24","district":"Banswara","district_code":"125","address1":"Banswara","address2":"","latitude":"24.1534","longitude":"74.3421","accuracy":"3"},{"address3":"Katumbi","state":"Rajasthan","state_code":"24","district":"Banswara","district_code":"125","address1":"Banswara","address2":"","latitude":"24.1534","longitude":"74.3421","accuracy":"3"},{"address3":"Kalakhet","state":"Rajasthan","state_code":"24","district":"Banswara","district_code":"125","address1":"Banswara","address2":"","latitude":"23.4752","longitude":"74.3639","accuracy":"3"},{"address3":"Kopda","state":"Rajasthan","state_code":"24","district":"Banswara","district_code":"125","address1":"Banswara","address2":"","latitude":"24.1534","longitude":"74.3421","accuracy":"3"},{"address3":"Banswara Prathvi Ganj","state":"Rajasthan","state_code":"24","district":"Banswara","district_code":"125","address1":"Banswara","address2":"","latitude":"24.1534","longitude":"74.3421","accuracy":"3"},{"address3":"Mokampura","state":"Rajasthan","state_code":"24","district":"Banswara","district_code":"125","address1":"Banswara","address2":"","latitude":"24.1534","longitude":"74.3421","accuracy":"3"},{"address3":"Kotra","state":"Rajasthan","state_code":"24","district":"Banswara","district_code":"125","address1":"Banswara","address2":"","latitude":"23.4588","longitude":"74.0707","accuracy":"4"},{"address3":"Mordi Nichali","state":"Rajasthan","state_code":"24","district":"Banswara","district_code":"125","address1":"Banswara","address2":"","latitude":"24.1534","longitude":"74.3421","accuracy":"3"},{"address3":"Bhapor","state":"Rajasthan","state_code":"24","district":"Banswara","district_code":"125","address1":"Banswara","address2":"","latitude":"24.1534","longitude":"74.3421","accuracy":"3"},{"address3":"Nalda","state":"Rajasthan","state_code":"24","district":"Banswara","district_code":"125","address1":"Banswara","address2":"","latitude":"24.1534","longitude":"74.3421","accuracy":"3"},{"address3":"Chanduji Ka Gara","state":"Rajasthan","state_code":"24","district":"Banswara","district_code":"125","address1":"Banswara","address2":"","latitude":"24.1534","longitude":"74.3421","accuracy":"3"},{"address3":"Danpur","state":"Rajasthan","state_code":"24","district":"Banswara","district_code":"125","address1":"Banswara","address2":"","latitude":"24.1534","longitude":"74.3421","accuracy":"3"},{"address3":"Banswara H.O","state":"Rajasthan","state_code":"24","district":"Banswara","district_code":"125","address1":"Banswara","address2":"","latitude":"24.1534","longitude":"74.3421","accuracy":"3"},{"address3":"Dana Khari","state":"Rajasthan","state_code":"24","district":"Banswara","district_code":"125","address1":"Banswara","address2":"","latitude":"24.1534","longitude":"74.3421","accuracy":"3"},{"address3":"Banswara Mahi Colony","state":"Rajasthan","state_code":"24","district":"Banswara","district_code":"125","address1":"Banswara","address2":"","latitude":"24.1534","longitude":"74.3421","accuracy":"3"},{"address3":"Galkiya","state":"Rajasthan","state_code":"24","district":"Banswara","district_code":"125","address1":"Banswara","address2":"","latitude":"24.1534","longitude":"74.3421","accuracy":"3"},{"address3":"Boriya","state":"Rajasthan","state_code":"24","district":"Banswara","district_code":"125","address1":"Banswara","address2":"","latitude":"24.1534","longitude":"74.3421","accuracy":"3"},{"address3":"Badliya","state":"Rajasthan","state_code":"24","district":"Banswara","district_code":"125","address1":"Banswara","address2":"","latitude":"24.1534","longitude":"74.3421","accuracy":"3"},{"address3":"Bari","state":"Rajasthan","state_code":"24","district":"Banswara","district_code":"125","address1":"Banswara","address2":"","latitude":"24.1534","longitude":"74.3421","accuracy":"3"},{"address3":"Sevna","state":"Rajasthan","state_code":"24","district":"Banswara","district_code":"125","address1":"Banswara","address2":"","latitude":"24.1534","longitude":"74.3421","accuracy":"3"},{"address3":"Chhoti Sarwan","state":"Rajasthan","state_code":"24","district":"Banswara","district_code":"125","address1":"Banswara","address2":"","latitude":"24.1534","longitude":"74.3421","accuracy":"3"},{"address3":"Navagoan","state":"Rajasthan","state_code":"24","district":"Banswara","district_code":"125","address1":"Banswara","address2":"","latitude":"24.1534","longitude":"74.3421","accuracy":"3"},{"address3":"Chriyawasa","state":"Rajasthan","state_code":"24","district":"Banswara","district_code":"125","address1":"Banswara","address2":"","latitude":"24.1534","longitude":"74.3421","accuracy":"3"},{"address3":"Bor Khaber","state":"Rajasthan","state_code":"24","district":"Banswara","district_code":"125","address1":"Banswara","address2":"","latitude":"24.1534","longitude":"74.3421","accuracy":"3"},{"address3":"Badrel Khurd","state":"Rajasthan","state_code":"24","district":"Banswara","district_code":"125","address1":"Banswara","address2":"","latitude":"24.1534","longitude":"74.3421","accuracy":"3"},{"address3":"Kuwania","state":"Rajasthan","state_code":"24","district":"Banswara","district_code":"125","address1":"NA","address2":"","latitude":"24.1534","longitude":"74.3421","accuracy":"3"},{"address3":"Palaswani","state":"Rajasthan","state_code":"24","district":"Banswara","district_code":"125","address1":"Banswara","address2":"","latitude":"24.1534","longitude":"74.3421","accuracy":"3"},{"address3":"Borwat","state":"Rajasthan","state_code":"24","district":"Banswara","district_code":"125","address1":"Banswara","address2":"","latitude":"24.1534","longitude":"74.3421","accuracy":"3"}],"327021":[{"address3":"Karanpur","state":"Rajasthan","state_code":"24","district":"Banswara","district_code":"125","address1":"Banswara","address2":"","latitude":"23.4752","longitude":"74.3639","accuracy":"3"},{"address3":"Ganoda","state":"Rajasthan","state_code":"24","district":"Banswara","district_code":"125","address1":"Banswara","address2":"","latitude":"24.7789","longitude":"74.1737","accuracy":"3"},{"address3":"Asan","state":"Rajasthan","state_code":"24","district":"Banswara","district_code":"125","address1":"Banswara","address2":"","latitude":"23.4752","longitude":"74.3639","accuracy":"4"},{"address3":"Amarsingh Ka Gara","state":"Rajasthan","state_code":"24","district":"Banswara","district_code":"125","address1":"Banswara","address2":"","latitude":"24.7789","longitude":"74.1737","accuracy":"3"},{"address3":"Borda","state":"Rajasthan","state_code":"24","district":"Banswara","district_code":"125","address1":"Banswara","address2":"","latitude":"23.4752","longitude":"74.3639","accuracy":"4"},{"address3":"Mota Tanda","state":"Rajasthan","state_code":"24","district":"Banswara","district_code":"125","address1":"Banswara","address2":"","latitude":"24.7789","longitude":"74.1737","accuracy":"3"},{"address3":"Bhimpur","state":"Rajasthan","state_code":"24","district":"Banswara","district_code":"125","address1":"Banswara","address2":"","latitude":"23.4752","longitude":"74.3639","accuracy":"4"},{"address3":"Bamanparda","state":"Rajasthan","state_code":"24","district":"Banswara","district_code":"125","address1":"Banswara","address2":"","latitude":"24.7789","longitude":"74.1737","accuracy":"3"},{"address3":"Buda Bassi","state":"Rajasthan","state_code":"24","district":"Banswara","district_code":"125","address1":"Banswara","address2":"","latitude":"24.7789","longitude":"74.1737","accuracy":"3"},{"address3":"Dukawara","state":"Rajasthan","state_code":"24","district":"Banswara","district_code":"125","address1":"Banswara","address2":"","latitude":"24.7789","longitude":"74.1737","accuracy":"3"},{"address3":"Mota Goan","state":"Rajasthan","state_code":"24","district":"Banswara","district_code":"125","address1":"Banswara","address2":"","latitude":"24.7789","longitude":"74.1737","accuracy":"3"},{"address3":"Bhoyar","state":"Rajasthan","state_code":"24","district":"Banswara","district_code":"125","address1":"Banswara","address2":"","latitude":"24.7789","longitude":"74.1737","accuracy":"3"},{"address3":"Bhuwasa","state":"Rajasthan","state_code":"24","district":"Banswara","district_code":"125","address1":"Banswara","address2":"","latitude":"24.7789","longitude":"74.1737","accuracy":"3"}],"327022":[{"address3":"Bori","state":"Rajasthan","state_code":"24","district":"Banswara","district_code":"125","address1":"NA","address2":"","latitude":"23.5778","longitude":"74.1088","accuracy":"4"},{"address3":"Asoda","state":"Rajasthan","state_code":"24","district":"Banswara","district_code":"125","address1":"Banswara","address2":"","latitude":"23.8307","longitude":"74.1586","accuracy":"3"},{"address3":"Khodan","state":"Rajasthan","state_code":"24","district":"Banswara","district_code":"125","address1":"Banswara","address2":"","latitude":"23.4752","longitude":"74.3639","accuracy":"3"},{"address3":"Mor","state":"Rajasthan","state_code":"24","district":"Banswara","district_code":"125","address1":"Banswara","address2":"","latitude":"23.2075","longitude":"74.4284","accuracy":"4"},{"address3":"Agarpura","state":"Rajasthan","state_code":"24","district":"Banswara","district_code":"125","address1":"Banswara","address2":"","latitude":"23.4752","longitude":"74.3639","accuracy":"4"},{"address3":"Chopasang","state":"Rajasthan","state_code":"24","district":"Banswara","district_code":"125","address1":"Banswara","address2":"","latitude":"23.8307","longitude":"74.1586","accuracy":"3"},{"address3":"Bhagora","state":"Rajasthan","state_code":"24","district":"Banswara","district_code":"125","address1":"Banswara","address2":"","latitude":"23.4752","longitude":"74.3639","accuracy":"4"},{"address3":"Jharas","state":"Rajasthan","state_code":"24","district":"Banswara","district_code":"125","address1":"NA","address2":"","latitude":"23.8307","longitude":"74.1586","accuracy":"3"},{"address3":"Berwa","state":"Rajasthan","state_code":"24","district":"Banswara","district_code":"125","address1":"Banswara","address2":"","latitude":"23.4752","longitude":"74.3639","accuracy":"4"},{"address3":"Daduka","state":"Rajasthan","state_code":"24","district":"Banswara","district_code":"125","address1":"Banswara","address2":"","latitude":"23.8307","longitude":"74.1586","accuracy":"3"},{"address3":"Garhi (Banswara)","state":"Rajasthan","state_code":"24","district":"Banswara","district_code":"125","address1":"Banswara","address2":"","latitude":"23.5901","longitude":"74.1482","accuracy":"4"},{"address3":"Kharan Ka Parda","state":"Rajasthan","state_code":"24","district":"Banswara","district_code":"125","address1":"Banswara","address2":"","latitude":"23.8307","longitude":"74.1586","accuracy":"3"},{"address3":"Matwala","state":"Rajasthan","state_code":"24","district":"Banswara","district_code":"125","address1":"Banswara","address2":"","latitude":"23.8307","longitude":"74.1586","accuracy":"3"},{"address3":"Naya Goan","state":"Rajasthan","state_code":"24","district":"Banswara","district_code":"125","address1":"Banswara","address2":"","latitude":"23.8307","longitude":"74.1586","accuracy":"3"},{"address3":"Samagarha","state":"Rajasthan","state_code":"24","district":"Banswara","district_code":"125","address1":"Banswara","address2":"","latitude":"23.8307","longitude":"74.1586","accuracy":"3"},{"address3":"Umbada","state":"Rajasthan","state_code":"24","district":"Banswara","district_code":"125","address1":"Banswara","address2":"","latitude":"23.8307","longitude":"74.1586","accuracy":"3"},{"address3":"Malana","state":"Rajasthan","state_code":"24","district":"Banswara","district_code":"125","address1":"Banswara","address2":"","latitude":"23.8307","longitude":"74.1586","accuracy":"3"}],"327023":[{"address3":"Ghatol","state":"Rajasthan","state_code":"24","district":"Banswara","district_code":"125","address1":"Banswara","address2":"","latitude":"23.7573","longitude":"74.4117","accuracy":"4"},{"address3":"Jagpura","state":"Rajasthan","state_code":"24","district":"Banswara","district_code":"125","address1":"Banswara","address2":"","latitude":"23.8633","longitude":"74.3545","accuracy":"4"},{"address3":"Devda","state":"Rajasthan","state_code":"24","district":"Banswara","district_code":"125","address1":"Banswara","address2":"","latitude":"23.8103","longitude":"74.3831","accuracy":"3"},{"address3":"Padoli Gordhan","state":"Rajasthan","state_code":"24","district":"Banswara","district_code":"125","address1":"Banswara","address2":"","latitude":"23.8103","longitude":"74.3831","accuracy":"3"},{"address3":"Amarthun","state":"Rajasthan","state_code":"24","district":"Banswara","district_code":"125","address1":"Banswara","address2":"","latitude":"23.8103","longitude":"74.3831","accuracy":"3"},{"address3":"Badana","state":"Rajasthan","state_code":"24","district":"Banswara","district_code":"125","address1":"Banswara","address2":"","latitude":"23.8103","longitude":"74.3831","accuracy":"3"},{"address3":"Dalwara Lokiya","state":"Rajasthan","state_code":"24","district":"Banswara","district_code":"125","address1":"Banswara","address2":"","latitude":"23.8103","longitude":"74.3831","accuracy":"3"},{"address3":"Doodka","state":"Rajasthan","state_code":"24","district":"Banswara","district_code":"125","address1":"Banswara","address2":"","latitude":"23.8103","longitude":"74.3831","accuracy":"3"},{"address3":"Jharkaniya","state":"Rajasthan","state_code":"24","district":"Banswara","district_code":"125","address1":"Banswara","address2":"","latitude":"23.8103","longitude":"74.3831","accuracy":"3"},{"address3":"Kanji Ka Gara","state":"Rajasthan","state_code":"24","district":"Banswara","district_code":"125","address1":"Banswara","address2":"","latitude":"23.8103","longitude":"74.3831","accuracy":"3"},{"address3":"Padal Badi","state":"Rajasthan","state_code":"24","district":"Banswara","district_code":"125","address1":"Banswara","address2":"","latitude":"23.8103","longitude":"74.3831","accuracy":"3"},{"address3":"Padoli Rathor","state":"Rajasthan","state_code":"24","district":"Banswara","district_code":"125","address1":"Banswara","address2":"","latitude":"23.8103","longitude":"74.3831","accuracy":"3"},{"address3":"Padal Chhoti","state":"Rajasthan","state_code":"24","district":"Banswara","district_code":"125","address1":"Banswara","address2":"","latitude":"23.8103","longitude":"74.3831","accuracy":"3"},{"address3":"Runjia","state":"Rajasthan","state_code":"24","district":"Banswara","district_code":"125","address1":"Banswara","address2":"","latitude":"23.8103","longitude":"74.3831","accuracy":"3"},{"address3":"Sanawasa","state":"Rajasthan","state_code":"24","district":"Banswara","district_code":"125","address1":"Banswara","address2":"","latitude":"23.8103","longitude":"74.3831","accuracy":"3"}],"327024":[{"address3":"Sakaria","state":"Rajasthan","state_code":"24","district":"Banswara","district_code":"125","address1":"Banswara","address2":"","latitude":"23.4752","longitude":"74.3639","accuracy":"4"},{"address3":"Saredi Chhoti","state":"Rajasthan","state_code":"24","district":"Banswara","district_code":"125","address1":"Banswara","address2":"","latitude":"24.5414","longitude":"74.4749","accuracy":"3"},{"address3":"Partapur","state":"Rajasthan","state_code":"24","district":"Banswara","district_code":"125","address1":"Banswara","address2":"","latitude":"23.5928","longitude":"74.174","accuracy":"4"},{"address3":"Kheda","state":"Rajasthan","state_code":"24","district":"Banswara","district_code":"125","address1":"Banswara","address2":"","latitude":"23.4752","longitude":"74.3639","accuracy":"4"},{"address3":"Badi Saredi","state":"Rajasthan","state_code":"24","district":"Banswara","district_code":"125","address1":"Banswara","address2":"","latitude":"24.5414","longitude":"74.4749","accuracy":"3"},{"address3":"Bhimsore","state":"Rajasthan","state_code":"24","district":"Banswara","district_code":"125","address1":"Banswara","address2":"","latitude":"24.5414","longitude":"74.4749","accuracy":"3"}],"327025":[{"address3":"Talwara","state":"Rajasthan","state_code":"24","district":"Banswara","district_code":"125","address1":"Banswara","address2":"","latitude":"23.5659","longitude":"74.3217","accuracy":"4"},{"address3":"Kushalpura","state":"Rajasthan","state_code":"24","district":"Banswara","district_code":"125","address1":"Banswara","address2":"","latitude":"23.4752","longitude":"74.3639","accuracy":"4"},{"address3":"Masotiya","state":"Rajasthan","state_code":"24","district":"Banswara","district_code":"125","address1":"Banswara","address2":"","latitude":"23.927","longitude":"75.3153","accuracy":"3"},{"address3":"Gamdi","state":"Rajasthan","state_code":"24","district":"Banswara","district_code":"125","address1":"Banswara","address2":"","latitude":"23.927","longitude":"75.3153","accuracy":"3"},{"address3":"Kunwala","state":"Rajasthan","state_code":"24","district":"Banswara","district_code":"125","address1":"Banswara","address2":"","latitude":"23.927","longitude":"75.3153","accuracy":"3"},{"address3":"Sagwadiya","state":"Rajasthan","state_code":"24","district":"Banswara","district_code":"125","address1":"Banswara","address2":"","latitude":"23.927","longitude":"75.3153","accuracy":"3"},{"address3":"Sundanpur","state":"Rajasthan","state_code":"24","district":"Banswara","district_code":"125","address1":"Banswara","address2":"","latitude":"23.927","longitude":"75.3153","accuracy":"3"},{"address3":"Bachadiya","state":"Rajasthan","state_code":"24","district":"Banswara","district_code":"125","address1":"Banswara","address2":"","latitude":"23.927","longitude":"75.3153","accuracy":"3"},{"address3":"Vajwanaia","state":"Rajasthan","state_code":"24","district":"Banswara","district_code":"125","address1":"Banswara","address2":"","latitude":"23.927","longitude":"75.3153","accuracy":"3"}],"327026":[{"address3":"Kherdabada","state":"Rajasthan","state_code":"24","district":"Banswara","district_code":"125","address1":"Banswara","address2":"","latitude":"24.1153","longitude":"74.3377","accuracy":"1"},{"address3":"Mahidam","state":"Rajasthan","state_code":"24","district":"Banswara","district_code":"125","address1":"Banswara","address2":"","latitude":"24.1153","longitude":"74.3377","accuracy":"1"},{"address3":"Bhungda","state":"Rajasthan","state_code":"24","district":"Banswara","district_code":"125","address1":"Banswara","address2":"","latitude":"24.1153","longitude":"74.3377","accuracy":"1"},{"address3":"Badgun","state":"Rajasthan","state_code":"24","district":"Banswara","district_code":"125","address1":"Banswara","address2":"","latitude":"24.1153","longitude":"74.3377","accuracy":"1"},{"address3":"Cheev","state":"Rajasthan","state_code":"24","district":"Banswara","district_code":"125","address1":"Banswara","address2":"","latitude":"24.1153","longitude":"74.3377","accuracy":"1"}],"327027":[{"address3":"Khamera","state":"Rajasthan","state_code":"24","district":"Banswara","district_code":"125","address1":"Banswara","address2":"","latitude":"23.7883","longitude":"74.4602","accuracy":"4"},{"address3":"Dungra","state":"Rajasthan","state_code":"24","district":"Banswara","district_code":"125","address1":"Banswara","address2":"","latitude":"23.1721","longitude":"74.3148","accuracy":"4"},{"address3":"Borpi Khera","state":"Rajasthan","state_code":"24","district":"Banswara","district_code":"125","address1":"Banswara","address2":"","latitude":"23.9717","longitude":"74.1147","accuracy":"3"},{"address3":"Kherwa","state":"Rajasthan","state_code":"24","district":"Banswara","district_code":"125","address1":"Banswara","address2":"","latitude":"23.4752","longitude":"74.3639","accuracy":"4"},{"address3":"Dungariya","state":"Rajasthan","state_code":"24","district":"Banswara","district_code":"125","address1":"Banswara","address2":"","latitude":"23.9717","longitude":"74.1147","accuracy":"3"},{"address3":"Kanthao","state":"Rajasthan","state_code":"24","district":"Banswara","district_code":"125","address1":"Banswara","address2":"","latitude":"23.9717","longitude":"74.1147","accuracy":"3"},{"address3":"Miyasa","state":"Rajasthan","state_code":"24","district":"Banswara","district_code":"125","address1":"Banswara","address2":"","latitude":"23.9717","longitude":"74.1147","accuracy":"3"},{"address3":"Mudsal","state":"Rajasthan","state_code":"24","district":"Banswara","district_code":"125","address1":"Banswara","address2":"","latitude":"23.9717","longitude":"74.1147","accuracy":"3"},{"address3":"Narwali","state":"Rajasthan","state_code":"24","district":"Banswara","district_code":"125","address1":"Banswara","address2":"","latitude":"23.9717","longitude":"74.1147","accuracy":"3"},{"address3":"Rupji Ka Kheda","state":"Rajasthan","state_code":"24","district":"Banswara","district_code":"125","address1":"Banswara","address2":"","latitude":"23.9717","longitude":"74.1147","accuracy":"3"},{"address3":"Sarodia","state":"Rajasthan","state_code":"24","district":"Banswara","district_code":"125","address1":"Banswara","address2":"","latitude":"23.9717","longitude":"74.1147","accuracy":"3"},{"address3":"Dagal","state":"Rajasthan","state_code":"24","district":"Banswara","district_code":"125","address1":"Banswara","address2":"","latitude":"23.2528","longitude":"74.2242","accuracy":"4"}],"327031":[{"address3":"Obla","state":"Rajasthan","state_code":"24","district":"Banswara","district_code":"125","address1":"Banswara","address2":"","latitude":"23.3551","longitude":"74.0246","accuracy":"4"},{"address3":"Barjodia","state":"Rajasthan","state_code":"24","district":"Banswara","district_code":"125","address1":"Banswara","address2":"","latitude":"23.8342","longitude":"74.0219","accuracy":"3"},{"address3":"Dokar","state":"Rajasthan","state_code":"24","district":"Banswara","district_code":"125","address1":"Banswara","address2":"","latitude":"23.4074","longitude":"74.0208","accuracy":"4"},{"address3":"Chhaja","state":"Rajasthan","state_code":"24","district":"Banswara","district_code":"125","address1":"Banswara","address2":"","latitude":"23.4258","longitude":"74.0585","accuracy":"4"},{"address3":"Bareth","state":"Rajasthan","state_code":"24","district":"Banswara","district_code":"125","address1":"Banswara","address2":"","latitude":"23.4752","longitude":"74.3639","accuracy":"4"},{"address3":"Naharpura","state":"Rajasthan","state_code":"24","district":"Banswara","district_code":"125","address1":"Banswara","address2":"","latitude":"23.4752","longitude":"74.3639","accuracy":"3"},{"address3":"Badliya","state":"Rajasthan","state_code":"24","district":"Banswara","district_code":"125","address1":"Banswara","address2":"","latitude":"23.8342","longitude":"74.0219","accuracy":"3"},{"address3":"Mundri","state":"Rajasthan","state_code":"24","district":"Banswara","district_code":"125","address1":"Banswara","address2":"","latitude":"23.3659","longitude":"74.075","accuracy":"4"},{"address3":"Ambalia","state":"Rajasthan","state_code":"24","district":"Banswara","district_code":"125","address1":"Banswara","address2":"","latitude":"23.8342","longitude":"74.0219","accuracy":"3"},{"address3":"Phalwa","state":"Rajasthan","state_code":"24","district":"Banswara","district_code":"125","address1":"Banswara","address2":"","latitude":"23.3157","longitude":"74.0931","accuracy":"4"},{"address3":"Sundrao","state":"Rajasthan","state_code":"24","district":"Banswara","district_code":"125","address1":"Banswara","address2":"","latitude":"23.8342","longitude":"74.0219","accuracy":"3"},{"address3":"Anandpuri (Banswara)","state":"Rajasthan","state_code":"24","district":"Banswara","district_code":"125","address1":"Banswara","address2":"","latitude":"23.8342","longitude":"74.0219","accuracy":"3"},{"address3":"Tamtiya","state":"Rajasthan","state_code":"24","district":"Banswara","district_code":"125","address1":"Banswara","address2":"","latitude":"23.8342","longitude":"74.0219","accuracy":"3"},{"address3":"Minapadar","state":"Rajasthan","state_code":"24","district":"Banswara","district_code":"125","address1":"Banswara","address2":"","latitude":"23.8342","longitude":"74.0219","accuracy":"3"},{"address3":"Madkola","state":"Rajasthan","state_code":"24","district":"Banswara","district_code":"125","address1":"Banswara","address2":"","latitude":"23.8342","longitude":"74.0219","accuracy":"3"},{"address3":"Kajelia","state":"Rajasthan","state_code":"24","district":"Banswara","district_code":"125","address1":"Banswara","address2":"","latitude":"23.8342","longitude":"74.0219","accuracy":"3"},{"address3":"Chandwara","state":"Rajasthan","state_code":"24","district":"Banswara","district_code":"125","address1":"Banswara","address2":"","latitude":"23.8342","longitude":"74.0219","accuracy":"3"},{"address3":"Cheekli Teja","state":"Rajasthan","state_code":"24","district":"Banswara","district_code":"125","address1":"Banswara","address2":"","latitude":"23.8342","longitude":"74.0219","accuracy":"3"}],"327032":[{"address3":"Biloda","state":"Rajasthan","state_code":"24","district":"Banswara","district_code":"125","address1":"Banswara","address2":"","latitude":"23.4752","longitude":"74.3639","accuracy":"3"},{"address3":"Ajna","state":"Rajasthan","state_code":"24","district":"Banswara","district_code":"125","address1":"Banswara","address2":"","latitude":"23.6063","longitude":"73.9834","accuracy":"3"},{"address3":"Paderi","state":"Rajasthan","state_code":"24","district":"Banswara","district_code":"125","address1":"Banswara","address2":"","latitude":"23.4752","longitude":"74.3639","accuracy":"4"},{"address3":"Saranpur","state":"Rajasthan","state_code":"24","district":"Banswara","district_code":"125","address1":"Banswara","address2":"","latitude":"23.4841","longitude":"74.0407","accuracy":"4"},{"address3":"Kotada","state":"Rajasthan","state_code":"24","district":"Banswara","district_code":"125","address1":"Banswara","address2":"","latitude":"23.6063","longitude":"73.9834","accuracy":"3"},{"address3":"Vakhatpura","state":"Rajasthan","state_code":"24","district":"Banswara","district_code":"125","address1":"Banswara","address2":"","latitude":"23.6063","longitude":"73.9834","accuracy":"3"},{"address3":"Nawadhara","state":"Rajasthan","state_code":"24","district":"Banswara","district_code":"125","address1":"Banswara","address2":"","latitude":"23.6063","longitude":"73.9834","accuracy":"3"},{"address3":"Kesharpura","state":"Rajasthan","state_code":"24","district":"Banswara","district_code":"125","address1":"Banswara","address2":"","latitude":"23.3404","longitude":"74.1774","accuracy":"4"},{"address3":"Bassi Badi","state":"Rajasthan","state_code":"24","district":"Banswara","district_code":"125","address1":"Banswara","address2":"","latitude":"23.6063","longitude":"73.9834","accuracy":"3"},{"address3":"Arthuna","state":"Rajasthan","state_code":"24","district":"Banswara","district_code":"125","address1":"Banswara","address2":"","latitude":"23.4995","longitude":"74.0961","accuracy":"4"},{"address3":"Panchawara","state":"Rajasthan","state_code":"24","district":"Banswara","district_code":"125","address1":"Banswara","address2":"","latitude":"23.6063","longitude":"73.9834","accuracy":"3"}],"327034":[{"address3":"Amja","state":"Rajasthan","state_code":"24","district":"Banswara","district_code":"125","address1":"Banswara","address2":"","latitude":"23.4453","longitude":"74.2148","accuracy":"3"},{"address3":"Raiyana","state":"Rajasthan","state_code":"24","district":"Banswara","district_code":"125","address1":"Banswara","address2":"","latitude":"23.3711","longitude":"74.2703","accuracy":"4"},{"address3":"Tamtiya Rathor","state":"Rajasthan","state_code":"24","district":"Banswara","district_code":"125","address1":"Banswara","address2":"","latitude":"23.4453","longitude":"74.2148","accuracy":"3"},{"address3":"Naugama","state":"Rajasthan","state_code":"24","district":"Banswara","district_code":"125","address1":"Banswara","address2":"","latitude":"23.4453","longitude":"74.2148","accuracy":"3"},{"address3":"Bhatar","state":"Rajasthan","state_code":"24","district":"Banswara","district_code":"125","address1":"Banswara","address2":"","latitude":"23.4866","longitude":"74.1794","accuracy":"4"},{"address3":"Paraheda","state":"Rajasthan","state_code":"24","district":"Banswara","district_code":"125","address1":"Banswara","address2":"","latitude":"23.4453","longitude":"74.2148","accuracy":"3"},{"address3":"Nahali","state":"Rajasthan","state_code":"24","district":"Banswara","district_code":"125","address1":"Banswara","address2":"","latitude":"23.4782","longitude":"74.1947","accuracy":"4"},{"address3":"Ador","state":"Rajasthan","state_code":"24","district":"Banswara","district_code":"125","address1":"Banswara","address2":"","latitude":"23.4453","longitude":"74.2148","accuracy":"3"},{"address3":"Pindarama","state":"Rajasthan","state_code":"24","district":"Banswara","district_code":"125","address1":"Banswara","address2":"","latitude":"23.4453","longitude":"74.2148","accuracy":"3"},{"address3":"Gopinath Ka Garha","state":"Rajasthan","state_code":"24","district":"Banswara","district_code":"125","address1":"Banswara","address2":"","latitude":"23.4453","longitude":"74.2148","accuracy":"3"},{"address3":"Jolana","state":"Rajasthan","state_code":"24","district":"Banswara","district_code":"125","address1":"Banswara","address2":"","latitude":"23.4453","longitude":"74.2148","accuracy":"3"},{"address3":"Odwara","state":"Rajasthan","state_code":"24","district":"Banswara","district_code":"125","address1":"Banswara","address2":"","latitude":"23.4453","longitude":"74.2148","accuracy":"3"},{"address3":"Panasi Chhti","state":"Rajasthan","state_code":"24","district":"Banswara","district_code":"125","address1":"NA","address2":"","latitude":"23.4453","longitude":"74.2148","accuracy":"3"},{"address3":"Madlada","state":"Rajasthan","state_code":"24","district":"Banswara","district_code":"125","address1":"Banswara","address2":"","latitude":"23.4453","longitude":"74.2148","accuracy":"3"}],"327601":[{"address3":"Handi","state":"Rajasthan","state_code":"24","district":"Banswara","district_code":"125","address1":"Banswara","address2":"","latitude":"23.1952","longitude":"74.1845","accuracy":"4"},{"address3":"Jambudi","state":"Rajasthan","state_code":"24","district":"Banswara","district_code":"125","address1":"Banswara","address2":"","latitude":"23.4752","longitude":"74.3639","accuracy":"4"},{"address3":"Lankai","state":"Rajasthan","state_code":"24","district":"Banswara","district_code":"125","address1":"Banswara","address2":"","latitude":"23.2234","longitude":"74.2075","accuracy":"4"},{"address3":"Salia","state":"Rajasthan","state_code":"24","district":"Banswara","district_code":"125","address1":"Banswara","address2":"","latitude":"23.4637","longitude":"74.3826","accuracy":"4"},{"address3":"Khunta Galia","state":"Rajasthan","state_code":"24","district":"Banswara","district_code":"125","address1":"Banswara","address2":"","latitude":"23.1823","longitude":"74.1346","accuracy":"4"},{"address3":"Udaipura","state":"Rajasthan","state_code":"24","district":"Banswara","district_code":"125","address1":"Banswara","address2":"","latitude":"23.4752","longitude":"74.3639","accuracy":"4"},{"address3":"Jher Moti","state":"Rajasthan","state_code":"24","district":"Banswara","district_code":"125","address1":"Banswara","address2":"","latitude":"23.2025","longitude":"74.2234","accuracy":"4"},{"address3":"Chordi","state":"Rajasthan","state_code":"24","district":"Banswara","district_code":"125","address1":"Banswara","address2":"","latitude":"23.4167","longitude":"74.1145","accuracy":"3"},{"address3":"Shergarh","state":"Rajasthan","state_code":"24","district":"Banswara","district_code":"125","address1":"Banswara","address2":"","latitude":"23.3425","longitude":"74.1709","accuracy":"4"},{"address3":"Sallopat","state":"Rajasthan","state_code":"24","district":"Banswara","district_code":"125","address1":"Banswara","address2":"","latitude":"23.1816","longitude":"74.1644","accuracy":"4"},{"address3":"Ramka Munna","state":"Rajasthan","state_code":"24","district":"Banswara","district_code":"125","address1":"Banswara","address2":"","latitude":"23.4167","longitude":"74.1145","accuracy":"3"},{"address3":"Rohaniya","state":"Rajasthan","state_code":"24","district":"Banswara","district_code":"125","address1":"Banswara","address2":"","latitude":"23.4167","longitude":"74.1145","accuracy":"3"},{"address3":"Gangad Talai","state":"Rajasthan","state_code":"24","district":"Banswara","district_code":"125","address1":"Banswara","address2":"","latitude":"23.4167","longitude":"74.1145","accuracy":"3"},{"address3":"Moti Timbi","state":"Rajasthan","state_code":"24","district":"Banswara","district_code":"125","address1":"Banswara","address2":"","latitude":"23.2771","longitude":"74.1438","accuracy":"4"},{"address3":"Dhalar","state":"Rajasthan","state_code":"24","district":"Banswara","district_code":"125","address1":"Banswara","address2":"","latitude":"23.4167","longitude":"74.1145","accuracy":"3"},{"address3":"Sangariya","state":"Rajasthan","state_code":"24","district":"Banswara","district_code":"125","address1":"Banswara","address2":"","latitude":"23.4167","longitude":"74.1145","accuracy":"3"},{"address3":"Khadalim","state":"Rajasthan","state_code":"24","district":"Banswara","district_code":"125","address1":"Banswara","address2":"","latitude":"23.4167","longitude":"74.1145","accuracy":"3"},{"address3":"Bagidora","state":"Rajasthan","state_code":"24","district":"Banswara","district_code":"125","address1":"Banswara","address2":"","latitude":"23.4043","longitude":"74.2675","accuracy":"4"},{"address3":"Rohanwari","state":"Rajasthan","state_code":"24","district":"Banswara","district_code":"125","address1":"Banswara","address2":"","latitude":"23.4167","longitude":"74.1145","accuracy":"3"},{"address3":"Ummadgarhi","state":"Rajasthan","state_code":"24","district":"Banswara","district_code":"125","address1":"Banswara","address2":"","latitude":"23.4167","longitude":"74.1145","accuracy":"3"},{"address3":"Jhanjharwa","state":"Rajasthan","state_code":"24","district":"Banswara","district_code":"125","address1":"Banswara","address2":"","latitude":"23.4167","longitude":"74.1145","accuracy":"3"},{"address3":"Bhaler Bhodar","state":"Rajasthan","state_code":"24","district":"Banswara","district_code":"125","address1":"Banswara","address2":"","latitude":"23.4167","longitude":"74.1145","accuracy":"3"}],"327602":[{"address3":"Himmatgarh","state":"Rajasthan","state_code":"24","district":"Banswara","district_code":"125","address1":"Banswara","address2":"","latitude":"23.1167","longitude":"74.3522","accuracy":"4"},{"address3":"Sajjan Garh","state":"Rajasthan","state_code":"24","district":"Banswara","district_code":"125","address1":"Banswara","address2":"","latitude":"23.2432","longitude":"74.2933","accuracy":"3"},{"address3":"Itala","state":"Rajasthan","state_code":"24","district":"Banswara","district_code":"125","address1":"Banswara","address2":"","latitude":"23.2927","longitude":"74.313","accuracy":"4"},{"address3":"Jalampura","state":"Rajasthan","state_code":"24","district":"Banswara","district_code":"125","address1":"Banswara","address2":"","latitude":"23.3914","longitude":"74.1934","accuracy":"4"},{"address3":"Tambesara","state":"Rajasthan","state_code":"24","district":"Banswara","district_code":"125","address1":"Banswara","address2":"","latitude":"23.2432","longitude":"74.2933","accuracy":"3"},{"address3":"Tandi Kalan","state":"Rajasthan","state_code":"24","district":"Banswara","district_code":"125","address1":"Banswara","address2":"","latitude":"23.2432","longitude":"74.2933","accuracy":"3"},{"address3":"Dungra Chhota","state":"Rajasthan","state_code":"24","district":"Banswara","district_code":"125","address1":"Banswara","address2":"","latitude":"23.1721","longitude":"74.3148","accuracy":"4"},{"address3":"Magarda Bada","state":"Rajasthan","state_code":"24","district":"Banswara","district_code":"125","address1":"Banswara","address2":"","latitude":"23.2432","longitude":"74.2933","accuracy":"3"},{"address3":"Tanda Mangla","state":"Rajasthan","state_code":"24","district":"Banswara","district_code":"125","address1":"Banswara","address2":"","latitude":"23.2432","longitude":"74.2933","accuracy":"3"},{"address3":"Machchar Para","state":"Rajasthan","state_code":"24","district":"Banswara","district_code":"125","address1":"Banswara","address2":"","latitude":"23.2432","longitude":"74.2933","accuracy":"3"},{"address3":"Rath Dhanraj","state":"Rajasthan","state_code":"24","district":"Banswara","district_code":"125","address1":"Banswara","address2":"","latitude":"23.2432","longitude":"74.2933","accuracy":"3"},{"address3":"Andheshwar","state":"Rajasthan","state_code":"24","district":"Banswara","district_code":"125","address1":"Banswara","address2":"","latitude":"23.2432","longitude":"74.2933","accuracy":"3"},{"address3":"Rohaniya Laxman Singh","state":"Rajasthan","state_code":"24","district":"Banswara","district_code":"125","address1":"Banswara","address2":"","latitude":"23.2432","longitude":"74.2933","accuracy":"3"},{"address3":"Chaura Kalan","state":"Rajasthan","state_code":"24","district":"Banswara","district_code":"125","address1":"Banswara","address2":"","latitude":"23.2432","longitude":"74.2933","accuracy":"3"},{"address3":"Mahudi Maska","state":"Rajasthan","state_code":"24","district":"Banswara","district_code":"125","address1":"Banswara","address2":"","latitude":"23.2432","longitude":"74.2933","accuracy":"3"},{"address3":"Khundni Rupa","state":"Rajasthan","state_code":"24","district":"Banswara","district_code":"125","address1":"Banswara","address2":"","latitude":"23.2432","longitude":"74.2933","accuracy":"3"},{"address3":"Dungra Kalan","state":"Rajasthan","state_code":"24","district":"Banswara","district_code":"125","address1":"Banswara","address2":"","latitude":"23.2432","longitude":"74.2933","accuracy":"3"},{"address3":"Godwara Noren","state":"Rajasthan","state_code":"24","district":"Banswara","district_code":"125","address1":"Banswara","address2":"","latitude":"23.2432","longitude":"74.2933","accuracy":"3"},{"address3":"Kesharwadi","state":"Rajasthan","state_code":"24","district":"Banswara","district_code":"125","address1":"Banswara","address2":"","latitude":"23.2432","longitude":"74.2933","accuracy":"3"}],"327603":[{"address3":"Balwara","state":"Rajasthan","state_code":"24","district":"Banswara","district_code":"125","address1":"Banswara","address2":"","latitude":"23.4752","longitude":"74.3639","accuracy":"4"},{"address3":"Patan","state":"Rajasthan","state_code":"24","district":"Banswara","district_code":"125","address1":"Banswara","address2":"","latitude":"23.4926","longitude":"74.3083","accuracy":"4"},{"address3":"Chhinch","state":"Rajasthan","state_code":"24","district":"Banswara","district_code":"125","address1":"Banswara","address2":"","latitude":"23.4663","longitude":"74.3105","accuracy":"4"},{"address3":"Bansala","state":"Rajasthan","state_code":"24","district":"Banswara","district_code":"125","address1":"Banswara","address2":"","latitude":"23.5954","longitude":"74.0852","accuracy":"3"},{"address3":"Naugama","state":"Rajasthan","state_code":"24","district":"Banswara","district_code":"125","address1":"Bagidora","address2":"","latitude":"23.5954","longitude":"74.0852","accuracy":"3"},{"address3":"Bodigama","state":"Rajasthan","state_code":"24","district":"Banswara","district_code":"125","address1":"Banswara","address2":"","latitude":"23.5954","longitude":"74.0852","accuracy":"3"},{"address3":"Pindarama","state":"Rajasthan","state_code":"24","district":"Banswara","district_code":"125","address1":"Bagidora","address2":"","latitude":"23.5954","longitude":"74.0852","accuracy":"3"}],"327604":[{"address3":"Limthan","state":"Rajasthan","state_code":"24","district":"Banswara","district_code":"125","address1":"Banswara","address2":"","latitude":"23.454","longitude":"74.4193","accuracy":"4"},{"address3":"Samaria","state":"Rajasthan","state_code":"24","district":"Banswara","district_code":"125","address1":"Banswara","address2":"","latitude":"23.4401","longitude":"74.3784","accuracy":"3"},{"address3":"Karji","state":"Rajasthan","state_code":"24","district":"Banswara","district_code":"125","address1":"Banswara","address2":"","latitude":"23.4009","longitude":"74.3846","accuracy":"4"},{"address3":"Pali Kalan","state":"Rajasthan","state_code":"24","district":"Banswara","district_code":"125","address1":"Banswara","address2":"","latitude":"23.4401","longitude":"74.3784","accuracy":"3"},{"address3":"Sagrod","state":"Rajasthan","state_code":"24","district":"Banswara","district_code":"125","address1":"Banswara","address2":"","latitude":"23.4806","longitude":"74.3655","accuracy":"4"},{"address3":"Saliya","state":"Rajasthan","state_code":"24","district":"Banswara","district_code":"125","address1":"Banswara","address2":"","latitude":"23.4401","longitude":"74.3784","accuracy":"3"},{"address3":"Surwania","state":"Rajasthan","state_code":"24","district":"Banswara","district_code":"125","address1":"Banswara","address2":"","latitude":"23.4391","longitude":"74.3731","accuracy":"4"},{"address3":"Bodigama","state":"Rajasthan","state_code":"24","district":"Banswara","district_code":"125","address1":"Banswara","address2":"","latitude":"23.4401","longitude":"74.3784","accuracy":"3"},{"address3":"Barodia","state":"Rajasthan","state_code":"24","district":"Banswara","district_code":"125","address1":"Banswara","address2":"","latitude":"23.4262","longitude":"74.3493","accuracy":"4"},{"address3":"Chokhala","state":"Rajasthan","state_code":"24","district":"Banswara","district_code":"125","address1":"Banswara","address2":"","latitude":"23.4401","longitude":"74.3784","accuracy":"3"},{"address3":"Budwa","state":"Rajasthan","state_code":"24","district":"Banswara","district_code":"125","address1":"Banswara","address2":"","latitude":"23.4401","longitude":"74.3784","accuracy":"3"}],"327605":[{"address3":"Paloda","state":"Rajasthan","state_code":"24","district":"Banswara","district_code":"125","address1":"Banswara","address2":"","latitude":"23.4018","longitude":"74.2169","accuracy":"1"},{"address3":"Lasada","state":"Rajasthan","state_code":"24","district":"Banswara","district_code":"125","address1":"Banswara","address2":"","latitude":"23.4018","longitude":"74.2169","accuracy":"1"},{"address3":"Akhebhanji Ka Gara","state":"Rajasthan","state_code":"24","district":"Banswara","district_code":"125","address1":"Banswara","address2":"","latitude":"23.4018","longitude":"74.2169","accuracy":"1"},{"address3":"Thikariya","state":"Rajasthan","state_code":"24","district":"Banswara","district_code":"125","address1":"Banswara","address2":"","latitude":"23.4018","longitude":"74.2169","accuracy":"1"},{"address3":"Luharia","state":"Rajasthan","state_code":"24","district":"Banswara","district_code":"125","address1":"Banswara","address2":"","latitude":"23.4018","longitude":"74.2169","accuracy":"1"}],"327606":[{"address3":"Kalinjara","state":"Rajasthan","state_code":"24","district":"Banswara","district_code":"125","address1":"Banswara","address2":"","latitude":"23.3466","longitude":"74.3037","accuracy":"4"},{"address3":"Biladi","state":"Rajasthan","state_code":"24","district":"Banswara","district_code":"125","address1":"Banswara","address2":"","latitude":"23.3512","longitude":"74.2851","accuracy":"3"},{"address3":"Sagwa","state":"Rajasthan","state_code":"24","district":"Banswara","district_code":"125","address1":"NA","address2":"","latitude":"23.3013","longitude":"74.2933","accuracy":"4"},{"address3":"Lilwani","state":"Rajasthan","state_code":"24","district":"Banswara","district_code":"125","address1":"Banswara","address2":"","latitude":"23.3488","longitude":"74.2431","accuracy":"4"},{"address3":"Mahudi","state":"Rajasthan","state_code":"24","district":"Banswara","district_code":"125","address1":"Banswara","address2":"","latitude":"23.3512","longitude":"74.2851","accuracy":"3"},{"address3":"Suwala","state":"Rajasthan","state_code":"24","district":"Banswara","district_code":"125","address1":"Banswara","address2":"","latitude":"23.3525","longitude":"74.2893","accuracy":"4"},{"address3":"Peeplod","state":"Rajasthan","state_code":"24","district":"Banswara","district_code":"125","address1":"Banswara","address2":"","latitude":"23.3512","longitude":"74.2851","accuracy":"3"},{"address3":"Rakho","state":"Rajasthan","state_code":"24","district":"Banswara","district_code":"125","address1":"Banswara","address2":"","latitude":"23.3743","longitude":"74.2821","accuracy":"4"},{"address3":"Nagawara","state":"Rajasthan","state_code":"24","district":"Banswara","district_code":"125","address1":"Banswara","address2":"","latitude":"23.3837","longitude":"74.2992","accuracy":"4"}],"327801":[{"address3":"Loharia","state":"Rajasthan","state_code":"24","district":"Banswara","district_code":"125","address1":"Banswara","address2":"","latitude":"23.7613","longitude":"74.2224","accuracy":"4"},{"address3":"Patan","state":"Rajasthan","state_code":"24","district":"Banswara","district_code":"125","address1":"Banswara","address2":"","latitude":"23.4926","longitude":"74.3083","accuracy":"4"},{"address3":"Ramgarh","state":"Rajasthan","state_code":"24","district":"Banswara","district_code":"125","address1":"Banswara","address2":"","latitude":"23.1494","longitude":"74.4776","accuracy":"4"},{"address3":"Bassi","state":"Rajasthan","state_code":"24","district":"Banswara","district_code":"125","address1":"Banswara","address2":"","latitude":"23.4752","longitude":"74.3639","accuracy":"4"},{"address3":"Kushalgarh","state":"Rajasthan","state_code":"24","district":"Banswara","district_code":"125","address1":"Banswara","address2":"","latitude":"23.199","longitude":"74.4507","accuracy":"4"},{"address3":"Dhumath","state":"Rajasthan","state_code":"24","district":"Banswara","district_code":"125","address1":"Banswara","address2":"","latitude":"23.4976","longitude":"74.2594","accuracy":"3"},{"address3":"Kushal Garh Bazar","state":"Rajasthan","state_code":"24","district":"Banswara","district_code":"125","address1":"Banswara","address2":"","latitude":"23.4976","longitude":"74.2594","accuracy":"3"},{"address3":"Mundri","state":"Rajasthan","state_code":"24","district":"Banswara","district_code":"125","address1":"Banswara","address2":"","latitude":"23.3659","longitude":"74.075","accuracy":"4"},{"address3":"Kalinjara","state":"Rajasthan","state_code":"24","district":"Banswara","district_code":"125","address1":"Banswara","address2":"","latitude":"23.3466","longitude":"74.3037","accuracy":"4"},{"address3":"Unkala","state":"Rajasthan","state_code":"24","district":"Banswara","district_code":"125","address1":"Banswara","address2":"","latitude":"23.4976","longitude":"74.2594","accuracy":"3"},{"address3":"Timbada","state":"Rajasthan","state_code":"24","district":"Banswara","district_code":"125","address1":"Banswara","address2":"","latitude":"23.4976","longitude":"74.2594","accuracy":"3"},{"address3":"Sabalpur","state":"Rajasthan","state_code":"24","district":"Banswara","district_code":"125","address1":"Banswara","address2":"","latitude":"23.4976","longitude":"74.2594","accuracy":"3"},{"address3":"Padikalan","state":"Rajasthan","state_code":"24","district":"Banswara","district_code":"125","address1":"Banswara","address2":"","latitude":"23.4976","longitude":"74.2594","accuracy":"3"},{"address3":"Mokampura","state":"Rajasthan","state_code":"24","district":"Banswara","district_code":"125","address1":"Banswara","address2":"","latitude":"23.4976","longitude":"74.2594","accuracy":"3"},{"address3":"Kushalapada","state":"Rajasthan","state_code":"24","district":"Banswara","district_code":"125","address1":"Banswara","address2":"","latitude":"23.4976","longitude":"74.2594","accuracy":"3"},{"address3":"Kotra Ranga","state":"Rajasthan","state_code":"24","district":"Banswara","district_code":"125","address1":"Banswara","address2":"","latitude":"23.4976","longitude":"74.2594","accuracy":"3"},{"address3":"Jhikali","state":"Rajasthan","state_code":"24","district":"Banswara","district_code":"125","address1":"Banswara","address2":"","latitude":"23.4976","longitude":"74.2594","accuracy":"3"},{"address3":"Badli Pada","state":"Rajasthan","state_code":"24","district":"Banswara","district_code":"125","address1":"Banswara","address2":"","latitude":"23.4976","longitude":"74.2594","accuracy":"3"},{"address3":"Chhoti Sarwa","state":"Rajasthan","state_code":"24","district":"Banswara","district_code":"125","address1":"Banswara","address2":"","latitude":"23.4976","longitude":"74.2594","accuracy":"3"},{"address3":"Charkani","state":"Rajasthan","state_code":"24","district":"Banswara","district_code":"125","address1":"Banswara","address2":"","latitude":"23.4976","longitude":"74.2594","accuracy":"3"},{"address3":"Badwasa","state":"Rajasthan","state_code":"24","district":"Banswara","district_code":"125","address1":"Banswara","address2":"","latitude":"23.4976","longitude":"74.2594","accuracy":"3"},{"address3":"Badi Sarwa","state":"Rajasthan","state_code":"24","district":"Banswara","district_code":"125","address1":"Banswara","address2":"","latitude":"23.4976","longitude":"74.2594","accuracy":"3"}],"credits":[{"name":"geonames","url":"https://www.geonames.org"}],"last_update":"2019-03-01T09:01:34.898Z"}